{
"meta":{"test_sets":[],"test_metrics":[],"learn_metrics":[{"best_value":"Min","name":"Logloss"}],"launch_mode":"Train","parameters":"","iteration_count":1000,"learn_sets":["learn"],"name":"experiment"},
"iterations":[
{"learn":[0.6877286391],"iteration":0,"passed_time":0.1394098542,"remaining_time":139.2704443},
{"learn":[0.6806845682],"iteration":1,"passed_time":0.1410341449,"remaining_time":70.37603833},
{"learn":[0.6756153298],"iteration":2,"passed_time":0.1420836613,"remaining_time":47.21913676},
{"learn":[0.6678378936],"iteration":3,"passed_time":0.1438278471,"remaining_time":35.81313394},
{"learn":[0.6606420813],"iteration":4,"passed_time":0.1457325955,"remaining_time":29.00078651},
{"learn":[0.6542231846],"iteration":5,"passed_time":0.1479494463,"remaining_time":24.5102916},
{"learn":[0.6486115291],"iteration":6,"passed_time":0.1499552289,"remaining_time":21.27222033},
{"learn":[0.6420208934],"iteration":7,"passed_time":0.1518398304,"remaining_time":18.82813897},
{"learn":[0.6362351162],"iteration":8,"passed_time":0.1534362543,"remaining_time":16.89503645},
{"learn":[0.6301985198],"iteration":9,"passed_time":0.1556860514,"remaining_time":15.41291909},
{"learn":[0.625545772],"iteration":10,"passed_time":0.1569116192,"remaining_time":14.10778104},
{"learn":[0.6200768347],"iteration":11,"passed_time":0.1585967474,"remaining_time":13.05779887},
{"learn":[0.6148832327],"iteration":12,"passed_time":0.160652426,"remaining_time":12.1972265},
{"learn":[0.6087367721],"iteration":13,"passed_time":0.1623598326,"remaining_time":11.43477107},
{"learn":[0.6057380521],"iteration":14,"passed_time":0.1635311231,"remaining_time":10.73854375},
{"learn":[0.6003345829],"iteration":15,"passed_time":0.1656949551,"remaining_time":10.19023974},
{"learn":[0.5940422594],"iteration":16,"passed_time":0.1674991143,"remaining_time":9.685389963},
{"learn":[0.5895537509],"iteration":17,"passed_time":0.1693041193,"remaining_time":9.236480285},
{"learn":[0.5842237573],"iteration":18,"passed_time":0.1713116411,"remaining_time":8.845090523},
{"learn":[0.5798839266],"iteration":19,"passed_time":0.1737504204,"remaining_time":8.513770597},
{"learn":[0.5763600669],"iteration":20,"passed_time":0.1768412106,"remaining_time":8.244168816},
{"learn":[0.5713296885],"iteration":21,"passed_time":0.1793312999,"remaining_time":7.972091424},
{"learn":[0.5669090632],"iteration":22,"passed_time":0.1834481582,"remaining_time":7.792558721},
{"learn":[0.5616819983],"iteration":23,"passed_time":0.1860686975,"remaining_time":7.566793698},
{"learn":[0.5572250269],"iteration":24,"passed_time":0.187883637,"remaining_time":7.327461844},
{"learn":[0.552959829],"iteration":25,"passed_time":0.1907569027,"remaining_time":7.146047047},
{"learn":[0.5486278422],"iteration":26,"passed_time":0.2091873301,"remaining_time":7.538491564},
{"learn":[0.5443717843],"iteration":27,"passed_time":0.2110255976,"remaining_time":7.325602887},
{"learn":[0.5406802915],"iteration":28,"passed_time":0.2137636308,"remaining_time":7.15739605},
{"learn":[0.5371909786],"iteration":29,"passed_time":0.2166407671,"remaining_time":7.004718136},
{"learn":[0.5331569589],"iteration":30,"passed_time":0.2185347202,"remaining_time":6.830972383},
{"learn":[0.5297575729],"iteration":31,"passed_time":0.2205119084,"remaining_time":6.670485229},
{"learn":[0.5259508436],"iteration":32,"passed_time":0.222414609,"remaining_time":6.517422028},
{"learn":[0.5224091599],"iteration":33,"passed_time":0.2242551383,"remaining_time":6.371484223},
{"learn":[0.5198511995],"iteration":34,"passed_time":0.2256367838,"remaining_time":6.221128467},
{"learn":[0.5165547425],"iteration":35,"passed_time":0.2274321558,"remaining_time":6.090127727},
{"learn":[0.5123043026],"iteration":36,"passed_time":0.2296571524,"remaining_time":5.977292913},
{"learn":[0.5088815018],"iteration":37,"passed_time":0.2314409246,"remaining_time":5.859109723},
{"learn":[0.5050067021],"iteration":38,"passed_time":0.2330400107,"remaining_time":5.742344879},
{"learn":[0.501817633],"iteration":39,"passed_time":0.234695063,"remaining_time":5.632681511},
{"learn":[0.498568165],"iteration":40,"passed_time":0.2366097835,"remaining_time":5.534360546},
{"learn":[0.4958044289],"iteration":41,"passed_time":0.2383228912,"remaining_time":5.436031661},
{"learn":[0.4920675135],"iteration":42,"passed_time":0.240067101,"remaining_time":5.342888736},
{"learn":[0.48914059],"iteration":43,"passed_time":0.2418567583,"remaining_time":5.254887748},
{"learn":[0.4861999916],"iteration":44,"passed_time":0.2437476728,"remaining_time":5.172867277},
{"learn":[0.4827357665],"iteration":45,"passed_time":0.2458573003,"remaining_time":5.098866619},
{"learn":[0.4796646993],"iteration":46,"passed_time":0.2474295645,"remaining_time":5.017029255},
{"learn":[0.4766285298],"iteration":47,"passed_time":0.2493427638,"remaining_time":4.945298148},
{"learn":[0.4750824823],"iteration":48,"passed_time":0.2507393266,"remaining_time":4.866389787},
{"learn":[0.4720316615],"iteration":49,"passed_time":0.2528031652,"remaining_time":4.803260139},
{"learn":[0.4691911143],"iteration":50,"passed_time":0.2544697381,"remaining_time":4.73513297},
{"learn":[0.4665319663],"iteration":51,"passed_time":0.256496177,"remaining_time":4.676122611},
{"learn":[0.464167188],"iteration":52,"passed_time":0.2581925734,"remaining_time":4.613365415},
{"learn":[0.4616578701],"iteration":53,"passed_time":0.2597423226,"remaining_time":4.550300689},
{"learn":[0.4589230254],"iteration":54,"passed_time":0.2618596974,"remaining_time":4.49922571},
{"learn":[0.4555597926],"iteration":55,"passed_time":0.2638216305,"remaining_time":4.447278914},
{"learn":[0.4529863661],"iteration":56,"passed_time":0.2655531298,"remaining_time":4.393273709},
{"learn":[0.4508435008],"iteration":57,"passed_time":0.2676225088,"remaining_time":4.346558677},
{"learn":[0.448112232],"iteration":58,"passed_time":0.2693492795,"remaining_time":4.295892745},
{"learn":[0.4454320261],"iteration":59,"passed_time":0.2711309251,"remaining_time":4.247717827},
{"learn":[0.442412059],"iteration":60,"passed_time":0.2733167903,"remaining_time":4.20728633},
{"learn":[0.4397345612],"iteration":61,"passed_time":0.2751948267,"remaining_time":4.16343141},
{"learn":[0.4372451812],"iteration":62,"passed_time":0.2768806944,"remaining_time":4.118050963},
{"learn":[0.4351082596],"iteration":63,"passed_time":0.2788607297,"remaining_time":4.078338171},
{"learn":[0.433623164],"iteration":64,"passed_time":0.2807231231,"remaining_time":4.038094156},
{"learn":[0.4310230938],"iteration":65,"passed_time":0.2824906671,"remaining_time":3.997670956},
{"learn":[0.4289021456],"iteration":66,"passed_time":0.284153013,"remaining_time":3.956936733},
{"learn":[0.426625838],"iteration":67,"passed_time":0.2858397514,"remaining_time":3.917686005},
{"learn":[0.4248576259],"iteration":68,"passed_time":0.2877237983,"remaining_time":3.882186322},
{"learn":[0.422193267],"iteration":69,"passed_time":0.2895526955,"remaining_time":3.846914382},
{"learn":[0.420079471],"iteration":70,"passed_time":0.2913380745,"remaining_time":3.812015087},
{"learn":[0.4183470831],"iteration":71,"passed_time":0.2933900892,"remaining_time":3.781472261},
{"learn":[0.4163983796],"iteration":72,"passed_time":0.2951388978,"remaining_time":3.747859702},
{"learn":[0.4139453604],"iteration":73,"passed_time":0.2966185291,"remaining_time":3.711739973},
{"learn":[0.4121305321],"iteration":74,"passed_time":0.2983020888,"remaining_time":3.679059096},
{"learn":[0.4104370991],"iteration":75,"passed_time":0.3000544214,"remaining_time":3.648030071},
{"learn":[0.408260448],"iteration":76,"passed_time":0.3017428301,"remaining_time":3.616995224},
{"learn":[0.4065380088],"iteration":77,"passed_time":0.3033995277,"remaining_time":3.586338007},
{"learn":[0.4053960596],"iteration":78,"passed_time":0.3047837011,"remaining_time":3.553237832},
{"learn":[0.4036587972],"iteration":79,"passed_time":0.3068909075,"remaining_time":3.529245436},
{"learn":[0.4018427768],"iteration":80,"passed_time":0.3089219448,"remaining_time":3.504929226},
{"learn":[0.400377972],"iteration":81,"passed_time":0.3108117259,"remaining_time":3.479575175},
{"learn":[0.3987597096],"iteration":82,"passed_time":0.3123224679,"remaining_time":3.450598832},
{"learn":[0.3971268719],"iteration":83,"passed_time":0.3140968176,"remaining_time":3.425151011},
{"learn":[0.3958139338],"iteration":84,"passed_time":0.3158256383,"remaining_time":3.399770106},
{"learn":[0.3941233268],"iteration":85,"passed_time":0.317428026,"remaining_time":3.373595532},
{"learn":[0.392508466],"iteration":86,"passed_time":0.3197834355,"remaining_time":3.355888237},
{"learn":[0.3907433906],"iteration":87,"passed_time":0.3215873746,"remaining_time":3.33281461},
{"learn":[0.3890271185],"iteration":88,"passed_time":0.3231956622,"remaining_time":3.308216273},
{"learn":[0.3874755755],"iteration":89,"passed_time":0.325467696,"remaining_time":3.290840037},
{"learn":[0.3854912445],"iteration":90,"passed_time":0.3272039142,"remaining_time":3.268443494},
{"learn":[0.3836759608],"iteration":91,"passed_time":0.3289703657,"remaining_time":3.246794478},
{"learn":[0.3820559677],"iteration":92,"passed_time":0.3310495619,"remaining_time":3.228623147},
{"learn":[0.3810531781],"iteration":93,"passed_time":0.3328965352,"remaining_time":3.208555967},
{"learn":[0.3796593831],"iteration":94,"passed_time":0.3349534781,"remaining_time":3.190872607},
{"learn":[0.3786880772],"iteration":95,"passed_time":0.3368409261,"remaining_time":3.171918721},
{"learn":[0.3773711021],"iteration":96,"passed_time":0.3384598725,"remaining_time":3.150817163},
{"learn":[0.3760747788],"iteration":97,"passed_time":0.3401683177,"remaining_time":3.130936965},
{"learn":[0.3743601675],"iteration":98,"passed_time":0.3418504379,"remaining_time":3.111184288},
{"learn":[0.373263886],"iteration":99,"passed_time":0.3436321336,"remaining_time":3.092689203},
{"learn":[0.3720837086],"iteration":100,"passed_time":0.3452287716,"remaining_time":3.072877878},
{"learn":[0.3707810344],"iteration":101,"passed_time":0.3473088734,"remaining_time":3.057680081},
{"learn":[0.3694040192],"iteration":102,"passed_time":0.3489761346,"remaining_time":3.039141677},
{"learn":[0.3679110512],"iteration":103,"passed_time":0.3507367766,"remaining_time":3.021732229},
{"learn":[0.3667115232],"iteration":104,"passed_time":0.3524919665,"remaining_time":3.004574381},
{"learn":[0.3653450042],"iteration":105,"passed_time":0.3542517141,"remaining_time":2.987745589},
{"learn":[0.3636539393],"iteration":106,"passed_time":0.3559721443,"remaining_time":2.970870325},
{"learn":[0.3626323985],"iteration":107,"passed_time":0.3577946995,"remaining_time":2.955119185},
{"learn":[0.3613856843],"iteration":108,"passed_time":0.359408917,"remaining_time":2.937920597},
{"learn":[0.3605606297],"iteration":109,"passed_time":0.3611711378,"remaining_time":2.922202842},
{"learn":[0.3591084478],"iteration":110,"passed_time":0.3631922747,"remaining_time":2.9088102},
{"learn":[0.3581100496],"iteration":111,"passed_time":0.3648107657,"remaining_time":2.892428214},
{"learn":[0.3569810974],"iteration":112,"passed_time":0.3664667127,"remaining_time":2.876601541},
{"learn":[0.3556398506],"iteration":113,"passed_time":0.3682208406,"remaining_time":2.861786533},
{"learn":[0.3548051052],"iteration":114,"passed_time":0.3700265247,"remaining_time":2.84759543},
{"learn":[0.3537211896],"iteration":115,"passed_time":0.3717771559,"remaining_time":2.833198326},
{"learn":[0.3525611779],"iteration":116,"passed_time":0.3737398661,"remaining_time":2.820617964},
{"learn":[0.3518299251],"iteration":117,"passed_time":0.3755766239,"remaining_time":2.807276121},
{"learn":[0.3509470472],"iteration":118,"passed_time":0.3774899683,"remaining_time":2.794694639},
{"learn":[0.3494469608],"iteration":119,"passed_time":0.3794093288,"remaining_time":2.782335078},
{"learn":[0.3484772016],"iteration":120,"passed_time":0.3812048309,"remaining_time":2.769248317},
{"learn":[0.3472123125],"iteration":121,"passed_time":0.3829695576,"remaining_time":2.756125177},
{"learn":[0.3461589295],"iteration":122,"passed_time":0.3849573709,"remaining_time":2.744777352},
{"learn":[0.3453252766],"iteration":123,"passed_time":0.3867527329,"remaining_time":2.73222092},
{"learn":[0.3443578794],"iteration":124,"passed_time":0.3891287,"remaining_time":2.7239009},
{"learn":[0.3434340054],"iteration":125,"passed_time":0.3911456886,"remaining_time":2.713185173},
{"learn":[0.3426185399],"iteration":126,"passed_time":0.3928474183,"remaining_time":2.70043934},
{"learn":[0.3419262455],"iteration":127,"passed_time":0.3948844868,"remaining_time":2.690150566},
{"learn":[0.3408799601],"iteration":128,"passed_time":0.3967550678,"remaining_time":2.678865613},
{"learn":[0.3402095552],"iteration":129,"passed_time":0.3986828891,"remaining_time":2.668108566},
{"learn":[0.3395644384],"iteration":130,"passed_time":0.4008703064,"remaining_time":2.659208369},
{"learn":[0.3387851054],"iteration":131,"passed_time":0.4029179967,"remaining_time":2.649491069},
{"learn":[0.3377519916],"iteration":132,"passed_time":0.4058924359,"remaining_time":2.64593039},
{"learn":[0.3366666921],"iteration":133,"passed_time":0.4076145474,"remaining_time":2.63428506},
{"learn":[0.3357293729],"iteration":134,"passed_time":0.4100427318,"remaining_time":2.627310837},
{"learn":[0.3349265895],"iteration":135,"passed_time":0.4119601996,"remaining_time":2.617158915},
{"learn":[0.3339765484],"iteration":136,"passed_time":0.413888563,"remaining_time":2.607195839},
{"learn":[0.3329982896],"iteration":137,"passed_time":0.4166832185,"remaining_time":2.602760394},
{"learn":[0.3323247556],"iteration":138,"passed_time":0.4185660235,"remaining_time":2.592700333},
{"learn":[0.3312297257],"iteration":139,"passed_time":0.4207457928,"remaining_time":2.584581299},
{"learn":[0.3304072798],"iteration":140,"passed_time":0.4227452416,"remaining_time":2.575447961},
{"learn":[0.3294967742],"iteration":141,"passed_time":0.4247221435,"remaining_time":2.566278867},
{"learn":[0.3288423797],"iteration":142,"passed_time":0.4271889898,"remaining_time":2.560146603},
{"learn":[0.3278807235],"iteration":143,"passed_time":0.4291642303,"remaining_time":2.551142924},
{"learn":[0.3267192337],"iteration":144,"passed_time":0.4316257691,"remaining_time":2.545103673},
{"learn":[0.3258779028],"iteration":145,"passed_time":0.433777656,"remaining_time":2.537302179},
{"learn":[0.3252702179],"iteration":146,"passed_time":0.4355350978,"remaining_time":2.527288697},
{"learn":[0.3245435203],"iteration":147,"passed_time":0.437810742,"remaining_time":2.520369947},
{"learn":[0.3235851378],"iteration":148,"passed_time":0.4395209037,"remaining_time":2.510283819},
{"learn":[0.3228612033],"iteration":149,"passed_time":0.4414601445,"remaining_time":2.501607485},
{"learn":[0.3220068494],"iteration":150,"passed_time":0.443543753,"remaining_time":2.493832095},
{"learn":[0.3210214181],"iteration":151,"passed_time":0.4452828636,"remaining_time":2.48420966},
{"learn":[0.3202281553],"iteration":152,"passed_time":0.4472957201,"remaining_time":2.476205719},
{"learn":[0.3194751386],"iteration":153,"passed_time":0.4490673322,"remaining_time":2.466954306},
{"learn":[0.3184148665],"iteration":154,"passed_time":0.4506234468,"remaining_time":2.456624597},
{"learn":[0.3175117055],"iteration":155,"passed_time":0.4522686848,"remaining_time":2.446889551},
{"learn":[0.316476498],"iteration":156,"passed_time":0.4541699668,"remaining_time":2.438632369},
{"learn":[0.3162888416],"iteration":157,"passed_time":0.4551969906,"remaining_time":2.425796621},
{"learn":[0.3156927667],"iteration":158,"passed_time":0.4568382315,"remaining_time":2.416358193},
{"learn":[0.3147662115],"iteration":159,"passed_time":0.4588833447,"remaining_time":2.40913756},
{"learn":[0.314026026],"iteration":160,"passed_time":0.4605890588,"remaining_time":2.400212549},
{"learn":[0.3133363737],"iteration":161,"passed_time":0.4622365824,"remaining_time":2.391075654},
{"learn":[0.3128925046],"iteration":162,"passed_time":0.4641147413,"remaining_time":2.38321496},
{"learn":[0.3120983374],"iteration":163,"passed_time":0.4657855466,"remaining_time":2.374370225},
{"learn":[0.3112547977],"iteration":164,"passed_time":0.4674131601,"remaining_time":2.365393871},
{"learn":[0.3105904449],"iteration":165,"passed_time":0.46938762,"remaining_time":2.358248645},
{"learn":[0.3096429151],"iteration":166,"passed_time":0.4711058842,"remaining_time":2.349887434},
{"learn":[0.3089070892],"iteration":167,"passed_time":0.4726323242,"remaining_time":2.34065532},
{"learn":[0.3079515546],"iteration":168,"passed_time":0.474725539,"remaining_time":2.334301319},
{"learn":[0.3073669041],"iteration":169,"passed_time":0.4765230578,"remaining_time":2.326553753},
{"learn":[0.3066929254],"iteration":170,"passed_time":0.4784143798,"remaining_time":2.319330531},
{"learn":[0.3060956503],"iteration":171,"passed_time":0.4806714354,"remaining_time":2.313929933},
{"learn":[0.3054715907],"iteration":172,"passed_time":0.4826871054,"remaining_time":2.30741177},
{"learn":[0.3048607529],"iteration":173,"passed_time":0.4846523037,"remaining_time":2.300705764},
{"learn":[0.3040428742],"iteration":174,"passed_time":0.486724284,"remaining_time":2.294557339},
{"learn":[0.3035596803],"iteration":175,"passed_time":0.4883721179,"remaining_time":2.286469461},
{"learn":[0.3028602503],"iteration":176,"passed_time":0.4903642131,"remaining_time":2.28005507},
{"learn":[0.3020387077],"iteration":177,"passed_time":0.4920194194,"remaining_time":2.272134622},
{"learn":[0.30145342],"iteration":178,"passed_time":0.4939383684,"remaining_time":2.265493857},
{"learn":[0.3010019466],"iteration":179,"passed_time":0.4961085148,"remaining_time":2.260049901},
{"learn":[0.3004864603],"iteration":180,"passed_time":0.4979741784,"remaining_time":2.253264376},
{"learn":[0.3003418622],"iteration":181,"passed_time":0.4990900456,"remaining_time":2.243162952},
{"learn":[0.2999712026],"iteration":182,"passed_time":0.5016382254,"remaining_time":2.239554263},
{"learn":[0.2991355705],"iteration":183,"passed_time":0.5035349272,"remaining_time":2.233067938},
{"learn":[0.2986799688],"iteration":184,"passed_time":0.5053847278,"remaining_time":2.226424611},
{"learn":[0.2980972271],"iteration":185,"passed_time":0.5072897564,"remaining_time":2.220074525},
{"learn":[0.2974451044],"iteration":186,"passed_time":0.5093384795,"remaining_time":2.214396705},
{"learn":[0.2968156014],"iteration":187,"passed_time":0.511474724,"remaining_time":2.20913551},
{"learn":[0.2962677481],"iteration":188,"passed_time":0.5134379607,"remaining_time":2.203165006},
{"learn":[0.2958312029],"iteration":189,"passed_time":0.5152720129,"remaining_time":2.19668595},
{"learn":[0.2953795822],"iteration":190,"passed_time":0.5173900096,"remaining_time":2.191458208},
{"learn":[0.2945906444],"iteration":191,"passed_time":0.5195138063,"remaining_time":2.186287268},
{"learn":[0.294181052],"iteration":192,"passed_time":0.5215659503,"remaining_time":2.1808483},
{"learn":[0.2934966772],"iteration":193,"passed_time":0.5233994226,"remaining_time":2.174535745},
{"learn":[0.292683831],"iteration":194,"passed_time":0.5253865179,"remaining_time":2.168903317},
{"learn":[0.2923366289],"iteration":195,"passed_time":0.5276975055,"remaining_time":2.164636706},
{"learn":[0.2919186798],"iteration":196,"passed_time":0.5293645685,"remaining_time":2.157765221},
{"learn":[0.2912172586],"iteration":197,"passed_time":0.531087811,"remaining_time":2.151173861},
{"learn":[0.2908728806],"iteration":198,"passed_time":0.5330722591,"remaining_time":2.145682812},
{"learn":[0.2901476929],"iteration":199,"passed_time":0.5349568297,"remaining_time":2.139827319},
{"learn":[0.2894615469],"iteration":200,"passed_time":0.5366270145,"remaining_time":2.133159127},
{"learn":[0.2891737338],"iteration":201,"passed_time":0.5386208292,"remaining_time":2.127818919},
{"learn":[0.2886429483],"iteration":202,"passed_time":0.5403058601,"remaining_time":2.121299362},
{"learn":[0.2882816796],"iteration":203,"passed_time":0.5418116131,"remaining_time":2.114127667},
{"learn":[0.2876571653],"iteration":204,"passed_time":0.5438038426,"remaining_time":2.108897829},
{"learn":[0.2872836814],"iteration":205,"passed_time":0.5456986316,"remaining_time":2.103323852},
{"learn":[0.2867894578],"iteration":206,"passed_time":0.5473701567,"remaining_time":2.096930117},
{"learn":[0.286368096],"iteration":207,"passed_time":0.5495356729,"remaining_time":2.092462754},
{"learn":[0.2861245841],"iteration":208,"passed_time":0.5510759293,"remaining_time":2.085651005},
{"learn":[0.2856295726],"iteration":209,"passed_time":0.5528095264,"remaining_time":2.07961679},
{"learn":[0.2852003342],"iteration":210,"passed_time":0.5551942846,"remaining_time":2.076058249},
{"learn":[0.2847343424],"iteration":211,"passed_time":0.5571671704,"remaining_time":2.07097986},
{"learn":[0.2842853646],"iteration":212,"passed_time":0.5594947979,"remaining_time":2.067241342},
{"learn":[0.2840660597],"iteration":213,"passed_time":0.5612752048,"remaining_time":2.061506126},
{"learn":[0.2837059361],"iteration":214,"passed_time":0.5630910006,"remaining_time":2.055936909},
{"learn":[0.2832441934],"iteration":215,"passed_time":0.5649202775,"remaining_time":2.050451378},
{"learn":[0.2830116514],"iteration":216,"passed_time":0.5663488353,"remaining_time":2.043553632},
{"learn":[0.2826501276],"iteration":217,"passed_time":0.5679598001,"remaining_time":2.037360384},
{"learn":[0.2821411446],"iteration":218,"passed_time":0.5698105779,"remaining_time":2.032064207},
{"learn":[0.2816106735],"iteration":219,"passed_time":0.5714083103,"remaining_time":2.025902191},
{"learn":[0.2812605033],"iteration":220,"passed_time":0.5731194792,"remaining_time":2.020181332},
{"learn":[0.2805938065],"iteration":221,"passed_time":0.5749063303,"remaining_time":2.014761824},
{"learn":[0.280152054],"iteration":222,"passed_time":0.576540015,"remaining_time":2.008841218},
{"learn":[0.2798100432],"iteration":223,"passed_time":0.5779330849,"remaining_time":2.00212533},
{"learn":[0.2795457228],"iteration":224,"passed_time":0.5796964966,"remaining_time":1.996732377},
{"learn":[0.2790229119],"iteration":225,"passed_time":0.5813319878,"remaining_time":1.990933445},
{"learn":[0.2782777435],"iteration":226,"passed_time":0.5831599728,"remaining_time":1.985826692},
{"learn":[0.2776643878],"iteration":227,"passed_time":0.5851896552,"remaining_time":1.981431639},
{"learn":[0.2771662322],"iteration":228,"passed_time":0.5870823289,"remaining_time":1.976595963},
{"learn":[0.276691542],"iteration":229,"passed_time":0.5887473033,"remaining_time":1.97102358},
{"learn":[0.2761213202],"iteration":230,"passed_time":0.5906797734,"remaining_time":1.966375523},
{"learn":[0.2756805672],"iteration":231,"passed_time":0.5925039993,"remaining_time":1.961392549},
{"learn":[0.2752644619],"iteration":232,"passed_time":0.5941520958,"remaining_time":1.955856899},
{"learn":[0.2749054655],"iteration":233,"passed_time":0.5959319314,"remaining_time":1.950785724},
{"learn":[0.2743910527],"iteration":234,"passed_time":0.5977636531,"remaining_time":1.945911467},
{"learn":[0.2740019877],"iteration":235,"passed_time":0.5993516915,"remaining_time":1.94027412},
{"learn":[0.2736647002],"iteration":236,"passed_time":0.601425359,"remaining_time":1.936234384},
{"learn":[0.2733198395],"iteration":237,"passed_time":0.6031290159,"remaining_time":1.931026513},
{"learn":[0.2729303957],"iteration":238,"passed_time":0.6047397241,"remaining_time":1.925552008},
{"learn":[0.2726533835],"iteration":239,"passed_time":0.6064102781,"remaining_time":1.920299214},
{"learn":[0.2720319887],"iteration":240,"passed_time":0.6081747554,"remaining_time":1.915371947},
{"learn":[0.2716841076],"iteration":241,"passed_time":0.6097999269,"remaining_time":1.910034482},
{"learn":[0.2712952344],"iteration":242,"passed_time":0.6118362978,"remaining_time":1.906008549},
{"learn":[0.2705793904],"iteration":243,"passed_time":0.6139246428,"remaining_time":1.902159959},
{"learn":[0.2697973556],"iteration":244,"passed_time":0.6157340764,"remaining_time":1.897466235},
{"learn":[0.2695684438],"iteration":245,"passed_time":0.6176337203,"remaining_time":1.89307246},
{"learn":[0.2691497361],"iteration":246,"passed_time":0.6193475984,"remaining_time":1.888132557},
{"learn":[0.2687440598],"iteration":247,"passed_time":0.6209486564,"remaining_time":1.882876571},
{"learn":[0.2682293097],"iteration":248,"passed_time":0.6228799206,"remaining_time":1.878645865},
{"learn":[0.2678457712],"iteration":249,"passed_time":0.6245269051,"remaining_time":1.873580715},
{"learn":[0.2675437326],"iteration":250,"passed_time":0.6262137325,"remaining_time":1.868661696},
{"learn":[0.267194013],"iteration":251,"passed_time":0.6281858465,"remaining_time":1.864615132},
{"learn":[0.2667944333],"iteration":252,"passed_time":0.6298666339,"remaining_time":1.859724805},
{"learn":[0.26641069],"iteration":253,"passed_time":0.631488893,"remaining_time":1.854687851},
{"learn":[0.2658035348],"iteration":254,"passed_time":0.6334151467,"remaining_time":1.850565821},
{"learn":[0.2651607934],"iteration":255,"passed_time":0.6350332874,"remaining_time":1.845565492},
{"learn":[0.2648379105],"iteration":256,"passed_time":0.6365999656,"remaining_time":1.840442702},
{"learn":[0.2644567133],"iteration":257,"passed_time":0.6385860509,"remaining_time":1.836553681},
{"learn":[0.2640802067],"iteration":258,"passed_time":0.6404870098,"remaining_time":1.832435808},
{"learn":[0.2632692268],"iteration":259,"passed_time":0.6424259764,"remaining_time":1.828443164},
{"learn":[0.262777818],"iteration":260,"passed_time":0.644740452,"remaining_time":1.825529479},
{"learn":[0.2624076047],"iteration":261,"passed_time":0.6464314578,"remaining_time":1.820864183},
{"learn":[0.2620632087],"iteration":262,"passed_time":0.6479865326,"remaining_time":1.815840587},
{"learn":[0.2616895179],"iteration":263,"passed_time":0.6501568605,"remaining_time":1.81255852},
{"learn":[0.2613634107],"iteration":264,"passed_time":0.6518041489,"remaining_time":1.807834149},
{"learn":[0.2610384607],"iteration":265,"passed_time":0.6534832313,"remaining_time":1.803220646},
{"learn":[0.2606573934],"iteration":266,"passed_time":0.6554603333,"remaining_time":1.799447282},
{"learn":[0.2602777068],"iteration":267,"passed_time":0.6571428772,"remaining_time":1.794882784},
{"learn":[0.259966151],"iteration":268,"passed_time":0.6586673505,"remaining_time":1.789910161},
{"learn":[0.2596193961],"iteration":269,"passed_time":0.6607580488,"remaining_time":1.786493984},
{"learn":[0.2592443614],"iteration":270,"passed_time":0.6625068035,"remaining_time":1.782167748},
{"learn":[0.2589163883],"iteration":271,"passed_time":0.6641482184,"remaining_time":1.777573173},
{"learn":[0.258620762],"iteration":272,"passed_time":0.6663544081,"remaining_time":1.77450423},
{"learn":[0.2581588373],"iteration":273,"passed_time":0.6680526049,"remaining_time":1.770095588},
{"learn":[0.2579425271],"iteration":274,"passed_time":0.6698424674,"remaining_time":1.765948323},
{"learn":[0.2576673049],"iteration":275,"passed_time":0.6717004324,"remaining_time":1.761996787},
{"learn":[0.2572529576],"iteration":276,"passed_time":0.6732762885,"remaining_time":1.757324031},
{"learn":[0.2565970479],"iteration":277,"passed_time":0.6750620987,"remaining_time":1.753218832},
{"learn":[0.255997034],"iteration":278,"passed_time":0.6769821634,"remaining_time":1.749477204},
{"learn":[0.2557197454],"iteration":279,"passed_time":0.6785257476,"remaining_time":1.744780494},
{"learn":[0.2555318383],"iteration":280,"passed_time":0.6804944885,"remaining_time":1.741194083},
{"learn":[0.2549461565],"iteration":281,"passed_time":0.682701371,"remaining_time":1.738225477},
{"learn":[0.2545343079],"iteration":282,"passed_time":0.6849450417,"remaining_time":1.735355459},
{"learn":[0.2541617196],"iteration":283,"passed_time":0.6869924918,"remaining_time":1.731995155},
{"learn":[0.2538195981],"iteration":284,"passed_time":0.6886359292,"remaining_time":1.727630489},
{"learn":[0.2534627315],"iteration":285,"passed_time":0.6904114348,"remaining_time":1.723614561},
{"learn":[0.2530788675],"iteration":286,"passed_time":0.6924249808,"remaining_time":1.720205614},
{"learn":[0.2525733291],"iteration":287,"passed_time":0.6943571294,"remaining_time":1.716605125},
{"learn":[0.2523632502],"iteration":288,"passed_time":0.6958842699,"remaining_time":1.712019778},
{"learn":[0.2520929053],"iteration":289,"passed_time":0.6978119637,"remaining_time":1.708436187},
{"learn":[0.2517383652],"iteration":290,"passed_time":0.6993499393,"remaining_time":1.703914457},
{"learn":[0.2516359877],"iteration":291,"passed_time":0.7004681159,"remaining_time":1.698395295},
{"learn":[0.2512744443],"iteration":292,"passed_time":0.7023419577,"remaining_time":1.69472957},
{"learn":[0.2510360038],"iteration":293,"passed_time":0.7039561663,"remaining_time":1.690452563},
{"learn":[0.2507619583],"iteration":294,"passed_time":0.705562122,"remaining_time":1.686173885},
{"learn":[0.2504182912],"iteration":295,"passed_time":0.7072757801,"remaining_time":1.682169423},
{"learn":[0.2501784575],"iteration":296,"passed_time":0.7092493281,"remaining_time":1.678795548},
{"learn":[0.24980888],"iteration":297,"passed_time":0.711137753,"remaining_time":1.675230546},
{"learn":[0.2493575049],"iteration":298,"passed_time":0.7130048642,"remaining_time":1.671626789},
{"learn":[0.2491542318],"iteration":299,"passed_time":0.7148630781,"remaining_time":1.668013849},
{"learn":[0.2487544177],"iteration":300,"passed_time":0.7166721225,"remaining_time":1.664298384},
{"learn":[0.2486006498],"iteration":301,"passed_time":0.7182264817,"remaining_time":1.660006901},
{"learn":[0.2480392765],"iteration":302,"passed_time":0.7199740342,"remaining_time":1.656177894},
{"learn":[0.2478016567],"iteration":303,"passed_time":0.7221103227,"remaining_time":1.653252581},
{"learn":[0.2474249849],"iteration":304,"passed_time":0.7240913879,"remaining_time":1.649978736},
{"learn":[0.247401129],"iteration":305,"passed_time":0.7251598635,"remaining_time":1.644643612},
{"learn":[0.2470076389],"iteration":306,"passed_time":0.7268099606,"remaining_time":1.640649195},
{"learn":[0.2466870413],"iteration":307,"passed_time":0.7286303033,"remaining_time":1.6370525},
{"learn":[0.2462779525],"iteration":308,"passed_time":0.7303343499,"remaining_time":1.633207235},
{"learn":[0.2460294273],"iteration":309,"passed_time":0.7320554806,"remaining_time":1.629413812},
{"learn":[0.2456329124],"iteration":310,"passed_time":0.7342285213,"remaining_time":1.626634891},
{"learn":[0.2451835148],"iteration":311,"passed_time":0.7359992291,"remaining_time":1.622972659},
{"learn":[0.2448901759],"iteration":312,"passed_time":0.737620017,"remaining_time":1.618993456},
{"learn":[0.2446457275],"iteration":313,"passed_time":0.7394452386,"remaining_time":1.615475903},
{"learn":[0.2442728937],"iteration":314,"passed_time":0.7410647568,"remaining_time":1.611521773},
{"learn":[0.2439288864],"iteration":315,"passed_time":0.7425941493,"remaining_time":1.607387336},
{"learn":[0.24372264],"iteration":316,"passed_time":0.744287593,"remaining_time":1.603622795},
{"learn":[0.2434955691],"iteration":317,"passed_time":0.7461646224,"remaining_time":1.600265008},
{"learn":[0.2430419066],"iteration":318,"passed_time":0.7477194119,"remaining_time":1.596228588},
{"learn":[0.2427087088],"iteration":319,"passed_time":0.7496824084,"remaining_time":1.593075118},
{"learn":[0.242452852],"iteration":320,"passed_time":0.7514614219,"remaining_time":1.589539892},
{"learn":[0.2421877003],"iteration":321,"passed_time":0.7531036536,"remaining_time":1.585727569},
{"learn":[0.241957002],"iteration":322,"passed_time":0.754777145,"remaining_time":1.581994202},
{"learn":[0.2416728822],"iteration":323,"passed_time":0.7566636122,"remaining_time":1.578717907},
{"learn":[0.2414159796],"iteration":324,"passed_time":0.7582613061,"remaining_time":1.574850405},
{"learn":[0.2412063286],"iteration":325,"passed_time":0.7600358745,"remaining_time":1.571362514},
{"learn":[0.2409507281],"iteration":326,"passed_time":0.7619557193,"remaining_time":1.568184095},
{"learn":[0.2407404701],"iteration":327,"passed_time":0.7635790654,"remaining_time":1.56440589},
{"learn":[0.2405010157],"iteration":328,"passed_time":0.7652014946,"remaining_time":1.560638915},
{"learn":[0.2402061806],"iteration":329,"passed_time":0.7671465888,"remaining_time":1.557540044},
{"learn":[0.2399052272],"iteration":330,"passed_time":0.7687504878,"remaining_time":1.553758539},
{"learn":[0.2396691831],"iteration":331,"passed_time":0.7703202386,"remaining_time":1.549921444},
{"learn":[0.239442177],"iteration":332,"passed_time":0.7722531213,"remaining_time":1.546825321},
{"learn":[0.2391999851],"iteration":333,"passed_time":0.7739601404,"remaining_time":1.543285789},
{"learn":[0.2389232008],"iteration":334,"passed_time":0.7756719793,"remaining_time":1.539766765},
{"learn":[0.2388788771],"iteration":335,"passed_time":0.7768833411,"remaining_time":1.53526946},
{"learn":[0.2388122195],"iteration":336,"passed_time":0.7782819225,"remaining_time":1.531159984},
{"learn":[0.2385906499],"iteration":337,"passed_time":0.7801882211,"remaining_time":1.528060954},
{"learn":[0.2382906676],"iteration":338,"passed_time":0.7819939467,"remaining_time":1.524772858},
{"learn":[0.2380717279],"iteration":339,"passed_time":0.783915718,"remaining_time":1.521718747},
{"learn":[0.2376277609],"iteration":340,"passed_time":0.7855407856,"remaining_time":1.518097882},
{"learn":[0.2373874826],"iteration":341,"passed_time":0.7875177636,"remaining_time":1.515165756},
{"learn":[0.2371589284],"iteration":342,"passed_time":0.7901214128,"remaining_time":1.513439557},
{"learn":[0.2369082132],"iteration":343,"passed_time":0.7916420316,"remaining_time":1.509642944},
{"learn":[0.2364397959],"iteration":344,"passed_time":0.7937047032,"remaining_time":1.506888639},
{"learn":[0.2361739228],"iteration":345,"passed_time":0.7953607062,"remaining_time":1.503369659},
{"learn":[0.2359858572],"iteration":346,"passed_time":0.7969380944,"remaining_time":1.499713474},
{"learn":[0.2357181708],"iteration":347,"passed_time":0.798908207,"remaining_time":1.496805032},
{"learn":[0.2352346351],"iteration":348,"passed_time":0.8006501449,"remaining_time":1.493476345},
{"learn":[0.234943478],"iteration":349,"passed_time":0.8023861941,"remaining_time":1.490145789},
{"learn":[0.2347026612],"iteration":350,"passed_time":0.8044559187,"remaining_time":1.487441286},
{"learn":[0.2343555371],"iteration":351,"passed_time":0.8067810405,"remaining_time":1.485210552},
{"learn":[0.234188554],"iteration":352,"passed_time":0.8088457798,"remaining_time":1.482502038},
{"learn":[0.2339112365],"iteration":353,"passed_time":0.810532955,"remaining_time":1.479108161},
{"learn":[0.2335526967],"iteration":354,"passed_time":0.8121432006,"remaining_time":1.475584125},
{"learn":[0.2332437225],"iteration":355,"passed_time":0.8140273359,"remaining_time":1.472566304},
{"learn":[0.2330424084],"iteration":356,"passed_time":0.8159354771,"remaining_time":1.469598072},
{"learn":[0.2326880593],"iteration":357,"passed_time":0.8176783508,"remaining_time":1.466339389},
{"learn":[0.2323424776],"iteration":358,"passed_time":0.8196171773,"remaining_time":1.463439027},
{"learn":[0.2321803825],"iteration":359,"passed_time":0.8215414716,"remaining_time":1.460518172},
{"learn":[0.2319101552],"iteration":360,"passed_time":0.8232530844,"remaining_time":1.457226374},
{"learn":[0.2318016834],"iteration":361,"passed_time":0.8257034743,"remaining_time":1.45524535},
{"learn":[0.2317799737],"iteration":362,"passed_time":0.826908466,"remaining_time":1.451076289},
{"learn":[0.2314884673],"iteration":363,"passed_time":0.8290376335,"remaining_time":1.448538283},
{"learn":[0.2311491036],"iteration":364,"passed_time":0.8312875268,"remaining_time":1.446212547},
{"learn":[0.2307757586],"iteration":365,"passed_time":0.83322965,"remaining_time":1.443354093},
{"learn":[0.2307558448],"iteration":366,"passed_time":0.8341748702,"remaining_time":1.438781179},
{"learn":[0.230445054],"iteration":367,"passed_time":0.8361321183,"remaining_time":1.435966029},
{"learn":[0.2302001481],"iteration":368,"passed_time":0.8377396414,"remaining_time":1.43255749},
{"learn":[0.2299287286],"iteration":369,"passed_time":0.8393062095,"remaining_time":1.429088951},
{"learn":[0.2299150091],"iteration":370,"passed_time":0.8403288637,"remaining_time":1.424708505},
{"learn":[0.2297767492],"iteration":371,"passed_time":0.8421881835,"remaining_time":1.421758546},
{"learn":[0.2294482817],"iteration":372,"passed_time":0.8437060464,"remaining_time":1.418240459},
{"learn":[0.2291204601],"iteration":373,"passed_time":0.8457269707,"remaining_time":1.41557509},
{"learn":[0.2289207409],"iteration":374,"passed_time":0.8474573774,"remaining_time":1.412428962},
{"learn":[0.2286723094],"iteration":375,"passed_time":0.8489798492,"remaining_time":1.408945282},
{"learn":[0.2283304801],"iteration":376,"passed_time":0.8509188233,"remaining_time":1.406160284},
{"learn":[0.2280789613],"iteration":377,"passed_time":0.8525189202,"remaining_time":1.402822139},
{"learn":[0.2278576327],"iteration":378,"passed_time":0.8540035758,"remaining_time":1.399304012},
{"learn":[0.2276178754],"iteration":379,"passed_time":0.8558413689,"remaining_time":1.39637276},
{"learn":[0.227453004],"iteration":380,"passed_time":0.8577077807,"remaining_time":1.393493743},
{"learn":[0.2273218922],"iteration":381,"passed_time":0.8593429062,"remaining_time":1.390245854},
{"learn":[0.2271254545],"iteration":382,"passed_time":0.8610968001,"remaining_time":1.387197717},
{"learn":[0.2266969964],"iteration":383,"passed_time":0.8628460888,"remaining_time":1.384148934},
{"learn":[0.226470192],"iteration":384,"passed_time":0.8645708976,"remaining_time":1.381067797},
{"learn":[0.2262248484],"iteration":385,"passed_time":0.8663265368,"remaining_time":1.378042729},
{"learn":[0.2259624198],"iteration":386,"passed_time":0.8681120256,"remaining_time":1.375071503},
{"learn":[0.2256466068],"iteration":387,"passed_time":0.8700088572,"remaining_time":1.372282012},
{"learn":[0.2253693336],"iteration":388,"passed_time":0.8717322034,"remaining_time":1.369224618},
{"learn":[0.2251053949],"iteration":389,"passed_time":0.8736751172,"remaining_time":1.366517491},
{"learn":[0.2248826193],"iteration":390,"passed_time":0.8752630693,"remaining_time":1.363261405},
{"learn":[0.2246525721],"iteration":391,"passed_time":0.8770013142,"remaining_time":1.360246936},
{"learn":[0.2242859931],"iteration":392,"passed_time":0.8790503506,"remaining_time":1.357718989},
{"learn":[0.223976575],"iteration":393,"passed_time":0.8808119709,"remaining_time":1.354751407},
{"learn":[0.2237443774],"iteration":394,"passed_time":0.8825373651,"remaining_time":1.351734445},
{"learn":[0.2236094607],"iteration":395,"passed_time":0.8844625779,"remaining_time":1.34902878},
{"learn":[0.223363337],"iteration":396,"passed_time":0.8862024649,"remaining_time":1.346045558},
{"learn":[0.2230866427],"iteration":397,"passed_time":0.8880077688,"remaining_time":1.34316753},
{"learn":[0.2229380616],"iteration":398,"passed_time":0.8896846441,"remaining_time":1.340101431},
{"learn":[0.2227287865],"iteration":399,"passed_time":0.8912450671,"remaining_time":1.336867601},
{"learn":[0.2222474619],"iteration":400,"passed_time":0.8929197957,"remaining_time":1.333812862},
{"learn":[0.2219963634],"iteration":401,"passed_time":0.8948640859,"remaining_time":1.331165978},
{"learn":[0.2218380683],"iteration":402,"passed_time":0.896429493,"remaining_time":1.327961309},
{"learn":[0.2215594805],"iteration":403,"passed_time":0.8981317718,"remaining_time":1.324966673},
{"learn":[0.2212898846],"iteration":404,"passed_time":0.9000371285,"remaining_time":1.322276769},
{"learn":[0.220952521],"iteration":405,"passed_time":0.9017104506,"remaining_time":1.31925125},
{"learn":[0.2206896248],"iteration":406,"passed_time":0.9032973906,"remaining_time":1.316106517},
{"learn":[0.2202655204],"iteration":407,"passed_time":0.9054234169,"remaining_time":1.313751625},
{"learn":[0.220061191],"iteration":408,"passed_time":0.906997052,"remaining_time":1.310599652},
{"learn":[0.2196759896],"iteration":409,"passed_time":0.9086349092,"remaining_time":1.307547796},
{"learn":[0.2194256991],"iteration":410,"passed_time":0.9106124005,"remaining_time":1.304989547},
{"learn":[0.2192128391],"iteration":411,"passed_time":0.9123226722,"remaining_time":1.302052746},
{"learn":[0.2189900396],"iteration":412,"passed_time":0.9140483567,"remaining_time":1.29914379},
{"learn":[0.2187155532],"iteration":413,"passed_time":0.9160818172,"remaining_time":1.296676195},
{"learn":[0.2183861094],"iteration":414,"passed_time":0.917898402,"remaining_time":1.293904976},
{"learn":[0.2180191227],"iteration":415,"passed_time":0.9195186255,"remaining_time":1.290862686},
{"learn":[0.2178960827],"iteration":416,"passed_time":0.9214141808,"remaining_time":1.288212152},
{"learn":[0.217588406],"iteration":417,"passed_time":0.9230637082,"remaining_time":1.285222675},
{"learn":[0.2172899041],"iteration":418,"passed_time":0.9246697898,"remaining_time":1.282179351},
{"learn":[0.2171138293],"iteration":419,"passed_time":0.9267595446,"remaining_time":1.2798108},
{"learn":[0.2167979147],"iteration":420,"passed_time":0.9290345125,"remaining_time":1.277698296},
{"learn":[0.216482529],"iteration":421,"passed_time":0.9315907709,"remaining_time":1.275970298},
{"learn":[0.2162662537],"iteration":422,"passed_time":0.9332972095,"remaining_time":1.273079172},
{"learn":[0.2159888149],"iteration":423,"passed_time":0.9350620424,"remaining_time":1.270272963},
{"learn":[0.2158732234],"iteration":424,"passed_time":0.9365044452,"remaining_time":1.267035426},
{"learn":[0.2157632865],"iteration":425,"passed_time":0.9382095527,"remaining_time":1.264160289},
{"learn":[0.2156318779],"iteration":426,"passed_time":0.9399092833,"remaining_time":1.261283418},
{"learn":[0.2153186365],"iteration":427,"passed_time":0.9419320044,"remaining_time":1.258843707},
{"learn":[0.2150242332],"iteration":428,"passed_time":0.9435078452,"remaining_time":1.255811141},
{"learn":[0.214912963],"iteration":429,"passed_time":0.945037614,"remaining_time":1.252724279},
{"learn":[0.2146722966],"iteration":430,"passed_time":0.9470516802,"remaining_time":1.250284005},
{"learn":[0.2145480689],"iteration":431,"passed_time":0.9486319007,"remaining_time":1.247275277},
{"learn":[0.2142473203],"iteration":432,"passed_time":0.9503666877,"remaining_time":1.244475547},
{"learn":[0.2140450131],"iteration":433,"passed_time":0.9522097691,"remaining_time":1.241821957},
{"learn":[0.2138715024],"iteration":434,"passed_time":0.954057578,"remaining_time":1.239178233},
{"learn":[0.2136478601],"iteration":435,"passed_time":0.9559993408,"remaining_time":1.236659698},
{"learn":[0.2134760551],"iteration":436,"passed_time":0.9583352198,"remaining_time":1.234651553},
{"learn":[0.2133614909],"iteration":437,"passed_time":0.9602756366,"remaining_time":1.232134493},
{"learn":[0.2131147742],"iteration":438,"passed_time":0.9620328782,"remaining_time":1.229385979},
{"learn":[0.2128956092],"iteration":439,"passed_time":0.9641981881,"remaining_time":1.22716133},
{"learn":[0.2126000715],"iteration":440,"passed_time":0.9661764472,"remaining_time":1.22469985},
{"learn":[0.2124850204],"iteration":441,"passed_time":0.9692556336,"remaining_time":1.223630415},
{"learn":[0.2122182461],"iteration":442,"passed_time":0.9716057308,"remaining_time":1.221635196},
{"learn":[0.2120650821],"iteration":443,"passed_time":0.9739643238,"remaining_time":1.219649018},
{"learn":[0.2118823747],"iteration":444,"passed_time":0.9760378618,"remaining_time":1.217305648},
{"learn":[0.2116043987],"iteration":445,"passed_time":0.9779519529,"remaining_time":1.21476543},
{"learn":[0.2113300063],"iteration":446,"passed_time":0.9799522541,"remaining_time":1.212334668},
{"learn":[0.211130831],"iteration":447,"passed_time":0.9821008824,"remaining_time":1.210088587},
{"learn":[0.21094614],"iteration":448,"passed_time":0.9840913054,"remaining_time":1.207648796},
{"learn":[0.210674581],"iteration":449,"passed_time":0.986158722,"remaining_time":1.205305105},
{"learn":[0.2103890488],"iteration":450,"passed_time":0.988913677,"remaining_time":1.203799576},
{"learn":[0.2099711973],"iteration":451,"passed_time":0.991311335,"remaining_time":1.201855335},
{"learn":[0.2097738602],"iteration":452,"passed_time":0.9934993161,"remaining_time":1.199655907},
{"learn":[0.2096811859],"iteration":453,"passed_time":0.9958450199,"remaining_time":1.197646213},
{"learn":[0.209444462],"iteration":454,"passed_time":0.9976055092,"remaining_time":1.194934071},
{"learn":[0.2093059526],"iteration":455,"passed_time":0.9992702384,"remaining_time":1.192111863},
{"learn":[0.209187751],"iteration":456,"passed_time":1.001253885,"remaining_time":1.189673653},
{"learn":[0.2090707107],"iteration":457,"passed_time":1.002894354,"remaining_time":1.18683131},
{"learn":[0.2088171399],"iteration":458,"passed_time":1.00439677,"remaining_time":1.183831487},
{"learn":[0.2086951375],"iteration":459,"passed_time":1.006337122,"remaining_time":1.181352273},
{"learn":[0.2085229839],"iteration":460,"passed_time":1.00807499,"remaining_time":1.178638654},
{"learn":[0.2082280682],"iteration":461,"passed_time":1.009800475,"remaining_time":1.175914839},
{"learn":[0.2080791158],"iteration":462,"passed_time":1.011812616,"remaining_time":1.173527807},
{"learn":[0.2078722431],"iteration":463,"passed_time":1.013419139,"remaining_time":1.170673833},
{"learn":[0.2077084821],"iteration":464,"passed_time":1.015018159,"remaining_time":1.167816591},
{"learn":[0.2075229862],"iteration":465,"passed_time":1.017161633,"remaining_time":1.165588653},
{"learn":[0.2072139139],"iteration":466,"passed_time":1.018759327,"remaining_time":1.162738161},
{"learn":[0.2069515981],"iteration":467,"passed_time":1.020458856,"remaining_time":1.160008785},
{"learn":[0.2067335798],"iteration":468,"passed_time":1.022484958,"remaining_time":1.157653546},
{"learn":[0.2064964543],"iteration":469,"passed_time":1.024028909,"remaining_time":1.154756004},
{"learn":[0.206354715],"iteration":470,"passed_time":1.025707705,"remaining_time":1.15201566},
{"learn":[0.2061613828],"iteration":471,"passed_time":1.027783951,"remaining_time":1.14972442},
{"learn":[0.2060319507],"iteration":472,"passed_time":1.029338139,"remaining_time":1.14685243},
{"learn":[0.2057385297],"iteration":473,"passed_time":1.030996482,"remaining_time":1.144101581},
{"learn":[0.2055488848],"iteration":474,"passed_time":1.032797098,"remaining_time":1.141512582},
{"learn":[0.2053251479],"iteration":475,"passed_time":1.034432604,"remaining_time":1.138745136},
{"learn":[0.2050022969],"iteration":476,"passed_time":1.036243769,"remaining_time":1.136175034},
{"learn":[0.2048508132],"iteration":477,"passed_time":1.038336962,"remaining_time":1.133916097},
{"learn":[0.2045942341],"iteration":478,"passed_time":1.040075157,"remaining_time":1.131271726},
{"learn":[0.2045282356],"iteration":479,"passed_time":1.041929401,"remaining_time":1.128756851},
{"learn":[0.2043459769],"iteration":480,"passed_time":1.04418573,"remaining_time":1.126678574},
{"learn":[0.204188609],"iteration":481,"passed_time":1.045952832,"remaining_time":1.12407379},
{"learn":[0.2040577552],"iteration":482,"passed_time":1.047733227,"remaining_time":1.121486705},
{"learn":[0.2039007909],"iteration":483,"passed_time":1.04964901,"remaining_time":1.119047291},
{"learn":[0.2036463269],"iteration":484,"passed_time":1.051643044,"remaining_time":1.116693129},
{"learn":[0.2034774897],"iteration":485,"passed_time":1.053990857,"remaining_time":1.11471461},
{"learn":[0.2033675041],"iteration":486,"passed_time":1.056281424,"remaining_time":1.112674272},
{"learn":[0.2031605871],"iteration":487,"passed_time":1.058128598,"remaining_time":1.11016771},
{"learn":[0.2028793252],"iteration":488,"passed_time":1.059918209,"remaining_time":1.107603691},
{"learn":[0.2028122105],"iteration":489,"passed_time":1.061590445,"remaining_time":1.104920668},
{"learn":[0.20271777],"iteration":490,"passed_time":1.063416232,"remaining_time":1.102400942},
{"learn":[0.2025653452],"iteration":491,"passed_time":1.065249457,"remaining_time":1.099891715},
{"learn":[0.2024925743],"iteration":492,"passed_time":1.0669906,"remaining_time":1.097290536},
{"learn":[0.2022632201],"iteration":493,"passed_time":1.068826032,"remaining_time":1.094789417},
{"learn":[0.2020729008],"iteration":494,"passed_time":1.070693517,"remaining_time":1.092323689},
{"learn":[0.2018345898],"iteration":495,"passed_time":1.072447681,"remaining_time":1.089745224},
{"learn":[0.2016681208],"iteration":496,"passed_time":1.074443013,"remaining_time":1.087414156},
{"learn":[0.2015282353],"iteration":497,"passed_time":1.076203684,"remaining_time":1.08484789},
{"learn":[0.201354298],"iteration":498,"passed_time":1.078025157,"remaining_time":1.082345899},
{"learn":[0.2010685044],"iteration":499,"passed_time":1.080085091,"remaining_time":1.080085091},
{"learn":[0.2009184185],"iteration":500,"passed_time":1.081781318,"remaining_time":1.077462829},
{"learn":[0.2007335637],"iteration":501,"passed_time":1.083311891,"remaining_time":1.074679924},
{"learn":[0.2004340942],"iteration":502,"passed_time":1.085237667,"remaining_time":1.072292486},
{"learn":[0.2003918689],"iteration":503,"passed_time":1.086453704,"remaining_time":1.069208407},
{"learn":[0.2001614493],"iteration":504,"passed_time":1.088223195,"remaining_time":1.06667422},
{"learn":[0.2000426679],"iteration":505,"passed_time":1.08990799,"remaining_time":1.06406037},
{"learn":[0.1998835522],"iteration":506,"passed_time":1.09170229,"remaining_time":1.061556665},
{"learn":[0.1997112067],"iteration":507,"passed_time":1.093422425,"remaining_time":1.058983923},
{"learn":[0.1995597611],"iteration":508,"passed_time":1.095169533,"remaining_time":1.056440551},
{"learn":[0.1992637157],"iteration":509,"passed_time":1.096915464,"remaining_time":1.053899171},
{"learn":[0.1990810548],"iteration":510,"passed_time":1.098591022,"remaining_time":1.051293561},
{"learn":[0.1988803769],"iteration":511,"passed_time":1.10021648,"remaining_time":1.048643833},
{"learn":[0.198577116],"iteration":512,"passed_time":1.102108617,"remaining_time":1.04625126},
{"learn":[0.1983671019],"iteration":513,"passed_time":1.103619329,"remaining_time":1.043499988},
{"learn":[0.1981003081],"iteration":514,"passed_time":1.105296143,"remaining_time":1.04090996},
{"learn":[0.1978512878],"iteration":515,"passed_time":1.107362451,"remaining_time":1.03868881},
{"learn":[0.1975712194],"iteration":516,"passed_time":1.109017771,"remaining_time":1.0360843},
{"learn":[0.1973725285],"iteration":517,"passed_time":1.110650859,"remaining_time":1.033462768},
{"learn":[0.1971135274],"iteration":518,"passed_time":1.112996114,"remaining_time":1.03150507},
{"learn":[0.1968520155],"iteration":519,"passed_time":1.114780113,"remaining_time":1.029027797},
{"learn":[0.1967834569],"iteration":520,"passed_time":1.116575702,"remaining_time":1.026563841},
{"learn":[0.196532871],"iteration":521,"passed_time":1.118499339,"remaining_time":1.024219702},
{"learn":[0.1962807635],"iteration":522,"passed_time":1.120472768,"remaining_time":1.021922582},
{"learn":[0.1960930313],"iteration":523,"passed_time":1.122449326,"remaining_time":1.01962954},
{"learn":[0.1959290013],"iteration":524,"passed_time":1.124269292,"remaining_time":1.017196026},
{"learn":[0.1957800635],"iteration":525,"passed_time":1.125997509,"remaining_time":1.014682166},
{"learn":[0.1954798911],"iteration":526,"passed_time":1.128089152,"remaining_time":1.012497474},
{"learn":[0.1953066573],"iteration":527,"passed_time":1.129869184,"remaining_time":1.010034574},
{"learn":[0.1950138416],"iteration":528,"passed_time":1.131641848,"remaining_time":1.007567694},
{"learn":[0.1947200643],"iteration":529,"passed_time":1.133699296,"remaining_time":1.00535598},
{"learn":[0.1944007122],"iteration":530,"passed_time":1.135892097,"remaining_time":1.003264395},
{"learn":[0.194095747],"iteration":531,"passed_time":1.138342741,"remaining_time":1.001399253},
{"learn":[0.1939911596],"iteration":532,"passed_time":1.140359946,"remaining_time":0.9991521479},
{"learn":[0.193758599],"iteration":533,"passed_time":1.142112583,"remaining_time":0.9966750255},
{"learn":[0.1935945448],"iteration":534,"passed_time":1.144322207,"remaining_time":0.9945978059},
{"learn":[0.1934702197],"iteration":535,"passed_time":1.146086664,"remaining_time":0.9921347244},
{"learn":[0.1933581399],"iteration":536,"passed_time":1.148280309,"remaining_time":0.9900442886},
{"learn":[0.1931464082],"iteration":537,"passed_time":1.150646791,"remaining_time":0.9881018913},
{"learn":[0.1929229245],"iteration":538,"passed_time":1.152688454,"remaining_time":0.9858801062},
{"learn":[0.1926735964],"iteration":539,"passed_time":1.154692119,"remaining_time":0.9836266201},
{"learn":[0.1925154427],"iteration":540,"passed_time":1.156645871,"remaining_time":0.9813317091},
{"learn":[0.1921888589],"iteration":541,"passed_time":1.158731683,"remaining_time":0.9791496511},
{"learn":[0.1920693264],"iteration":542,"passed_time":1.160876854,"remaining_time":0.9770179047},
{"learn":[0.1918637672],"iteration":543,"passed_time":1.162889812,"remaining_time":0.9747752833},
{"learn":[0.1916393122],"iteration":544,"passed_time":1.164901059,"remaining_time":0.9725320769},
{"learn":[0.1915976654],"iteration":545,"passed_time":1.166948002,"remaining_time":0.9703194012},
{"learn":[0.191401958],"iteration":546,"passed_time":1.168637097,"remaining_time":0.9678109777},
{"learn":[0.1911751293],"iteration":547,"passed_time":1.17083236,"remaining_time":0.9657230411},
{"learn":[0.1909466855],"iteration":548,"passed_time":1.172607625,"remaining_time":0.9632896883},
{"learn":[0.1907654488],"iteration":549,"passed_time":1.174464258,"remaining_time":0.9609253017},
{"learn":[0.190539377],"iteration":550,"passed_time":1.176790902,"remaining_time":0.9589457623},
{"learn":[0.1902131901],"iteration":551,"passed_time":1.179035739,"remaining_time":0.9568985707},
{"learn":[0.1899986477],"iteration":552,"passed_time":1.181151296,"remaining_time":0.9547461654},
{"learn":[0.1896592673],"iteration":553,"passed_time":1.183254894,"remaining_time":0.9525842652},
{"learn":[0.1893525712],"iteration":554,"passed_time":1.184990175,"remaining_time":0.9501272578},
{"learn":[0.1892287124],"iteration":555,"passed_time":1.187014543,"remaining_time":0.9479036995},
{"learn":[0.1890468897],"iteration":556,"passed_time":1.188682748,"remaining_time":0.9453975897},
{"learn":[0.1887978122],"iteration":557,"passed_time":1.190705498,"remaining_time":0.9431753228},
{"learn":[0.1884837364],"iteration":558,"passed_time":1.193041999,"remaining_time":0.9412012907},
{"learn":[0.1880942491],"iteration":559,"passed_time":1.194876717,"remaining_time":0.9388317062},
{"learn":[0.187902383],"iteration":560,"passed_time":1.196743184,"remaining_time":0.9364888729},
{"learn":[0.1877623893],"iteration":561,"passed_time":1.198679153,"remaining_time":0.9342019021},
{"learn":[0.1875472654],"iteration":562,"passed_time":1.200577844,"remaining_time":0.9318872429},
{"learn":[0.1873480716],"iteration":563,"passed_time":1.202635493,"remaining_time":0.9296969418},
{"learn":[0.1871204583],"iteration":564,"passed_time":1.204523178,"remaining_time":0.9273762517},
{"learn":[0.1868492406],"iteration":565,"passed_time":1.206321202,"remaining_time":0.9249883419},
{"learn":[0.1867210608],"iteration":566,"passed_time":1.208244916,"remaining_time":0.9226984983},
{"learn":[0.1864396814],"iteration":567,"passed_time":1.209865707,"remaining_time":0.920179552},
{"learn":[0.1863167212],"iteration":568,"passed_time":1.211500357,"remaining_time":0.9176742596},
{"learn":[0.1860911301],"iteration":569,"passed_time":1.213532504,"remaining_time":0.915471889},
{"learn":[0.1857533195],"iteration":570,"passed_time":1.215075191,"remaining_time":0.9129023767},
{"learn":[0.1854156983],"iteration":571,"passed_time":1.216837161,"remaining_time":0.9105005329},
{"learn":[0.1852433584],"iteration":572,"passed_time":1.219491158,"remaining_time":0.908765662},
{"learn":[0.1849714502],"iteration":573,"passed_time":1.221525205,"remaining_time":0.9065674869},
{"learn":[0.1847872319],"iteration":574,"passed_time":1.223620952,"remaining_time":0.9044154864},
{"learn":[0.1846305037],"iteration":575,"passed_time":1.225369812,"remaining_time":0.9020083338},
{"learn":[0.1845128389],"iteration":576,"passed_time":1.227030543,"remaining_time":0.8995388555},
{"learn":[0.1843104907],"iteration":577,"passed_time":1.228864353,"remaining_time":0.8971985412},
{"learn":[0.1841181415],"iteration":578,"passed_time":1.230761885,"remaining_time":0.8949063104},
{"learn":[0.1838602751],"iteration":579,"passed_time":1.232623097,"remaining_time":0.892589139},
{"learn":[0.1837405031],"iteration":580,"passed_time":1.234659057,"remaining_time":0.8903995612},
{"learn":[0.1836367947],"iteration":581,"passed_time":1.236484329,"remaining_time":0.8880591916},
{"learn":[0.1835002742],"iteration":582,"passed_time":1.238276724,"remaining_time":0.8856970733},
{"learn":[0.1833739681],"iteration":583,"passed_time":1.240352412,"remaining_time":0.8835387044},
{"learn":[0.1831484494],"iteration":584,"passed_time":1.242006668,"remaining_time":0.881081653},
{"learn":[0.1829201897],"iteration":585,"passed_time":1.243566825,"remaining_time":0.878560863},
{"learn":[0.1827316798],"iteration":586,"passed_time":1.24561265,"remaining_time":0.8763850501},
{"learn":[0.182493451],"iteration":587,"passed_time":1.247151451,"remaining_time":0.8738544182},
{"learn":[0.1823408278],"iteration":588,"passed_time":1.248756506,"remaining_time":0.8713733855},
{"learn":[0.1822193956],"iteration":589,"passed_time":1.250563204,"remaining_time":0.8690354466},
{"learn":[0.1818820819],"iteration":590,"passed_time":1.252200575,"remaining_time":0.866582124},
{"learn":[0.1817195134],"iteration":591,"passed_time":1.25394301,"remaining_time":0.8642039661},
{"learn":[0.1815384664],"iteration":592,"passed_time":1.255743703,"remaining_time":0.861867938},
{"learn":[0.1813379418],"iteration":593,"passed_time":1.257474638,"remaining_time":0.8594860324},
{"learn":[0.1811255667],"iteration":594,"passed_time":1.259238071,"remaining_time":0.8571284349},
{"learn":[0.1809122422],"iteration":595,"passed_time":1.26114153,"remaining_time":0.8548677482},
{"learn":[0.1807115651],"iteration":596,"passed_time":1.263010904,"remaining_time":0.8525852499},
{"learn":[0.180590908],"iteration":597,"passed_time":1.264609208,"remaining_time":0.8501219091},
{"learn":[0.1803590201],"iteration":598,"passed_time":1.266285477,"remaining_time":0.8477136497},
{"learn":[0.1801701824],"iteration":599,"passed_time":1.268223657,"remaining_time":0.8454824383},
{"learn":[0.1800064104],"iteration":600,"passed_time":1.269781915,"remaining_time":0.8429999732},
{"learn":[0.1799088727],"iteration":601,"passed_time":1.271521617,"remaining_time":0.8406405373},
{"learn":[0.1797667682],"iteration":602,"passed_time":1.27351715,"remaining_time":0.8384515897},
{"learn":[0.1796704404],"iteration":603,"passed_time":1.275124017,"remaining_time":0.8360084617},
{"learn":[0.1795219515],"iteration":604,"passed_time":1.276894225,"remaining_time":0.8336747417},
{"learn":[0.1792937208],"iteration":605,"passed_time":1.27857865,"remaining_time":0.831287109},
{"learn":[0.1790409289],"iteration":606,"passed_time":1.280125557,"remaining_time":0.8288127575},
{"learn":[0.1787174591],"iteration":607,"passed_time":1.28184919,"remaining_time":0.8264553985},
{"learn":[0.1784747192],"iteration":608,"passed_time":1.283585909,"remaining_time":0.824108523},
{"learn":[0.1783131662],"iteration":609,"passed_time":1.285084681,"remaining_time":0.8216115176},
{"learn":[0.1781245214],"iteration":610,"passed_time":1.286635638,"remaining_time":0.8191510034},
{"learn":[0.1780327895],"iteration":611,"passed_time":1.288741012,"remaining_time":0.8170449552},
{"learn":[0.1777582514],"iteration":612,"passed_time":1.290438618,"remaining_time":0.8146814767},
{"learn":[0.1775868871],"iteration":613,"passed_time":1.291941208,"remaining_time":0.8121975675},
{"learn":[0.1775264276],"iteration":614,"passed_time":1.293750288,"remaining_time":0.8099087168},
{"learn":[0.1772949368],"iteration":615,"passed_time":1.295564104,"remaining_time":0.8076243763},
{"learn":[0.1769960552],"iteration":616,"passed_time":1.297223599,"remaining_time":0.805245767},
{"learn":[0.1767493711],"iteration":617,"passed_time":1.299175904,"remaining_time":0.8030504777},
{"learn":[0.1765814056],"iteration":618,"passed_time":1.301124854,"remaining_time":0.8008539088},
{"learn":[0.1763562425],"iteration":619,"passed_time":1.302902072,"remaining_time":0.798552883},
{"learn":[0.176215985],"iteration":620,"passed_time":1.305478489,"remaining_time":0.7967413},
{"learn":[0.1759941824],"iteration":621,"passed_time":1.307315922,"remaining_time":0.7944781647},
{"learn":[0.1757759612],"iteration":622,"passed_time":1.309371914,"remaining_time":0.7923486542},
{"learn":[0.1755764191],"iteration":623,"passed_time":1.311024114,"remaining_time":0.7899760686},
{"learn":[0.1753708794],"iteration":624,"passed_time":1.312634187,"remaining_time":0.7875805119},
{"learn":[0.1750929839],"iteration":625,"passed_time":1.314352531,"remaining_time":0.7852521512},
{"learn":[0.1750016333],"iteration":626,"passed_time":1.316358714,"remaining_time":0.7830969704},
{"learn":[0.1747816966],"iteration":627,"passed_time":1.31802744,"remaining_time":0.7807423692},
{"learn":[0.1747697793],"iteration":628,"passed_time":1.319054604,"remaining_time":0.7780115393},
{"learn":[0.1746607759],"iteration":629,"passed_time":1.320972579,"remaining_time":0.7758092926},
{"learn":[0.1744719403],"iteration":630,"passed_time":1.322564209,"remaining_time":0.7734171049},
{"learn":[0.1743800927],"iteration":631,"passed_time":1.324174839,"remaining_time":0.7710385137},
{"learn":[0.1741362645],"iteration":632,"passed_time":1.326083304,"remaining_time":0.7688350278},
{"learn":[0.1740305304],"iteration":633,"passed_time":1.327607787,"remaining_time":0.7664108048},
{"learn":[0.1739062542],"iteration":634,"passed_time":1.329363732,"remaining_time":0.7641224601},
{"learn":[0.173722659],"iteration":635,"passed_time":1.331502371,"remaining_time":0.7620548162},
{"learn":[0.1735628236],"iteration":636,"passed_time":1.333212273,"remaining_time":0.7597426295},
{"learn":[0.1734215249],"iteration":637,"passed_time":1.33501468,"remaining_time":0.7574848187},
{"learn":[0.1731335218],"iteration":638,"passed_time":1.337160312,"remaining_time":0.7554223357},
{"learn":[0.1729638476],"iteration":639,"passed_time":1.338849241,"remaining_time":0.7531026979},
{"learn":[0.1727043572],"iteration":640,"passed_time":1.34045352,"remaining_time":0.7507376189},
{"learn":[0.1725718523],"iteration":641,"passed_time":1.342371543,"remaining_time":0.7485498637},
{"learn":[0.1723834682],"iteration":642,"passed_time":1.343925622,"remaining_time":0.746160882},
{"learn":[0.1721989806],"iteration":643,"passed_time":1.345558046,"remaining_time":0.7438178017},
{"learn":[0.1719881177],"iteration":644,"passed_time":1.34744076,"remaining_time":0.7416146818},
{"learn":[0.1718382828],"iteration":645,"passed_time":1.34906909,"remaining_time":0.7392731547},
{"learn":[0.1714897468],"iteration":646,"passed_time":1.35063628,"remaining_time":0.7369004742},
{"learn":[0.1712585706],"iteration":647,"passed_time":1.352542099,"remaining_time":0.7347142267},
{"learn":[0.1711529242],"iteration":648,"passed_time":1.354041247,"remaining_time":0.7323089023},
{"learn":[0.1710092652],"iteration":649,"passed_time":1.355791356,"remaining_time":0.7300414996},
{"learn":[0.1708424967],"iteration":650,"passed_time":1.358165515,"remaining_time":0.7281102375},
{"learn":[0.1706230596],"iteration":651,"passed_time":1.359793923,"remaining_time":0.7257795783},
{"learn":[0.1704657513],"iteration":652,"passed_time":1.361289282,"remaining_time":0.7233803688},
{"learn":[0.1701360806],"iteration":653,"passed_time":1.363652222,"remaining_time":0.7214429189},
{"learn":[0.1699732423],"iteration":654,"passed_time":1.366670659,"remaining_time":0.7198494311},
{"learn":[0.1697920373],"iteration":655,"passed_time":1.370409335,"remaining_time":0.7186292856},
{"learn":[0.1696328694],"iteration":656,"passed_time":1.373453533,"remaining_time":0.717038907},
{"learn":[0.1695475997],"iteration":657,"passed_time":1.375805328,"remaining_time":0.7150842283},
{"learn":[0.1693792186],"iteration":658,"passed_time":1.378204256,"remaining_time":0.7131527336},
{"learn":[0.1692622124],"iteration":659,"passed_time":1.380816378,"remaining_time":0.7113296491},
{"learn":[0.1690799356],"iteration":660,"passed_time":1.384301727,"remaining_time":0.7099520202},
{"learn":[0.1689814837],"iteration":661,"passed_time":1.387516659,"remaining_time":0.7084299558},
{"learn":[0.1688061639],"iteration":662,"passed_time":1.390785309,"remaining_time":0.706930089},
{"learn":[0.1687079844],"iteration":663,"passed_time":1.39394707,"remaining_time":0.7053708064},
{"learn":[0.168608108],"iteration":664,"passed_time":1.396788215,"remaining_time":0.7036451912},
{"learn":[0.1684314198],"iteration":665,"passed_time":1.399162405,"remaining_time":0.701682047},
{"learn":[0.168158319],"iteration":666,"passed_time":1.400928783,"remaining_time":0.6994142201},
{"learn":[0.1680267256],"iteration":667,"passed_time":1.402872278,"remaining_time":0.6972359224},
{"learn":[0.1678789476],"iteration":668,"passed_time":1.405585777,"remaining_time":0.6954393009},
{"learn":[0.1677215633],"iteration":669,"passed_time":1.408590882,"remaining_time":0.6937835686},
{"learn":[0.1675457295],"iteration":670,"passed_time":1.411090705,"remaining_time":0.6918760685},
{"learn":[0.1673732785],"iteration":671,"passed_time":1.412943169,"remaining_time":0.6896508326},
{"learn":[0.1672231421],"iteration":672,"passed_time":1.414821496,"remaining_time":0.6874392706},
{"learn":[0.1669454159],"iteration":673,"passed_time":1.416694177,"remaining_time":0.6852259668},
{"learn":[0.1668096999],"iteration":674,"passed_time":1.418666119,"remaining_time":0.6830614649},
{"learn":[0.1666660267],"iteration":675,"passed_time":1.420477291,"remaining_time":0.6808204766},
{"learn":[0.1665177741],"iteration":676,"passed_time":1.422275205,"remaining_time":0.678574433},
{"learn":[0.1663628291],"iteration":677,"passed_time":1.423897103,"remaining_time":0.676246117},
{"learn":[0.166236225],"iteration":678,"passed_time":1.426474616,"remaining_time":0.6743716521},
{"learn":[0.1659756061],"iteration":679,"passed_time":1.428848559,"remaining_time":0.672399322},
{"learn":[0.1658554953],"iteration":680,"passed_time":1.430782321,"remaining_time":0.6702196186},
{"learn":[0.1657299758],"iteration":681,"passed_time":1.432693295,"remaining_time":0.6680300114},
{"learn":[0.1655003647],"iteration":682,"passed_time":1.434285409,"remaining_time":0.665693228},
{"learn":[0.165262515],"iteration":683,"passed_time":1.436089032,"remaining_time":0.6634563362},
{"learn":[0.1651018771],"iteration":684,"passed_time":1.438189145,"remaining_time":0.661357052},
{"learn":[0.1648755278],"iteration":685,"passed_time":1.439895902,"remaining_time":0.6590777162},
{"learn":[0.1646710371],"iteration":686,"passed_time":1.441790426,"remaining_time":0.6568855945},
{"learn":[0.1645223223],"iteration":687,"passed_time":1.443709697,"remaining_time":0.6547055602},
{"learn":[0.1644113374],"iteration":688,"passed_time":1.445353307,"remaining_time":0.6524018557},
{"learn":[0.1643404839],"iteration":689,"passed_time":1.44722858,"remaining_time":0.6502041447},
{"learn":[0.1641690871],"iteration":690,"passed_time":1.449099175,"remaining_time":0.6480052753},
{"learn":[0.1640139195],"iteration":691,"passed_time":1.45105494,"remaining_time":0.6458452622},
{"learn":[0.1638518443],"iteration":692,"passed_time":1.453044062,"remaining_time":0.6437006161},
{"learn":[0.1637422191],"iteration":693,"passed_time":1.454749021,"remaining_time":0.6414311244},
{"learn":[0.1636437525],"iteration":694,"passed_time":1.456503314,"remaining_time":0.6391849075},
{"learn":[0.1634901511],"iteration":695,"passed_time":1.45849679,"remaining_time":0.6370445751},
{"learn":[0.1633241435],"iteration":696,"passed_time":1.460018656,"remaining_time":0.6346996455},
{"learn":[0.1631714155],"iteration":697,"passed_time":1.461712605,"remaining_time":0.6324315281},
{"learn":[0.1629779958],"iteration":698,"passed_time":1.463818389,"remaining_time":0.6303423965},
{"learn":[0.1628240896],"iteration":699,"passed_time":1.465828215,"remaining_time":0.6282120922},
{"learn":[0.1626542292],"iteration":700,"passed_time":1.467402445,"remaining_time":0.6258963351},
{"learn":[0.1626283977],"iteration":701,"passed_time":1.468887392,"remaining_time":0.6235447903},
{"learn":[0.1623856735],"iteration":702,"passed_time":1.470519589,"remaining_time":0.6212579204},
{"learn":[0.1621787675],"iteration":703,"passed_time":1.472151657,"remaining_time":0.6189728556},
{"learn":[0.1619571364],"iteration":704,"passed_time":1.474048568,"remaining_time":0.6168004648},
{"learn":[0.1617846692],"iteration":705,"passed_time":1.475893541,"remaining_time":0.6146072255},
{"learn":[0.1617451654],"iteration":706,"passed_time":1.477395811,"remaining_time":0.6122729459},
{"learn":[0.1614485493],"iteration":707,"passed_time":1.479359288,"remaining_time":0.6101312319},
{"learn":[0.1613312598],"iteration":708,"passed_time":1.481470628,"remaining_time":0.6080507089},
{"learn":[0.1610514299],"iteration":709,"passed_time":1.483069448,"remaining_time":0.6057607606},
{"learn":[0.1608600941],"iteration":710,"passed_time":1.48534725,"remaining_time":0.6037487417},
{"learn":[0.1606878231],"iteration":711,"passed_time":1.48766121,"remaining_time":0.601750602},
{"learn":[0.1604897537],"iteration":712,"passed_time":1.490452044,"remaining_time":0.5999435297},
{"learn":[0.1603835515],"iteration":713,"passed_time":1.493228806,"remaining_time":0.5981280652},
{"learn":[0.160205814],"iteration":714,"passed_time":1.495381159,"remaining_time":0.5960610214},
{"learn":[0.1600460037],"iteration":715,"passed_time":1.497380054,"remaining_time":0.5939328705},
{"learn":[0.1598388091],"iteration":716,"passed_time":1.499086943,"remaining_time":0.5916898254},
{"learn":[0.1596666028],"iteration":717,"passed_time":1.501351328,"remaining_time":0.5896672347},
{"learn":[0.1595223291],"iteration":718,"passed_time":1.503052953,"remaining_time":0.5874240329},
{"learn":[0.1593094061],"iteration":719,"passed_time":1.505068913,"remaining_time":0.5853045772},
{"learn":[0.1592397288],"iteration":720,"passed_time":1.507197287,"remaining_time":0.5832289085},
{"learn":[0.1590436797],"iteration":721,"passed_time":1.509049261,"remaining_time":0.5810466682},
{"learn":[0.1588727373],"iteration":722,"passed_time":1.511025184,"remaining_time":0.5789128299},
{"learn":[0.1587481093],"iteration":723,"passed_time":1.51299524,"remaining_time":0.5767771911},
{"learn":[0.1586130998],"iteration":724,"passed_time":1.514753578,"remaining_time":0.574561702},
{"learn":[0.1585485949],"iteration":725,"passed_time":1.516900897,"remaining_time":0.5724942781},
{"learn":[0.1584877197],"iteration":726,"passed_time":1.518723148,"remaining_time":0.5703045658},
{"learn":[0.1583493524],"iteration":727,"passed_time":1.52083615,"remaining_time":0.5682244957},
{"learn":[0.1582192482],"iteration":728,"passed_time":1.522742181,"remaining_time":0.5660673952},
{"learn":[0.158153186],"iteration":729,"passed_time":1.524766337,"remaining_time":0.5639546726},
{"learn":[0.1579959583],"iteration":730,"passed_time":1.526972634,"remaining_time":0.5619092183},
{"learn":[0.1577842141],"iteration":731,"passed_time":1.528871531,"remaining_time":0.5597507793},
{"learn":[0.1576174456],"iteration":732,"passed_time":1.5305958,"remaining_time":0.5575294387},
{"learn":[0.1574331302],"iteration":733,"passed_time":1.532938605,"remaining_time":0.5555336088},
{"learn":[0.157289655],"iteration":734,"passed_time":1.534857759,"remaining_time":0.55338409},
{"learn":[0.1571594302],"iteration":735,"passed_time":1.536652494,"remaining_time":0.5511905685},
{"learn":[0.1570202348],"iteration":736,"passed_time":1.538726504,"remaining_time":0.5490977892},
{"learn":[0.1569079833],"iteration":737,"passed_time":1.540705128,"remaining_time":0.5469711971},
{"learn":[0.1567777245],"iteration":738,"passed_time":1.542604236,"remaining_time":0.5448169224},
{"learn":[0.1566209175],"iteration":739,"passed_time":1.544647861,"remaining_time":0.5427141132},
{"learn":[0.1565129584],"iteration":740,"passed_time":1.546698979,"remaining_time":0.540614083},
{"learn":[0.1563362811],"iteration":741,"passed_time":1.549357153,"remaining_time":0.5387252634},
{"learn":[0.1561305442],"iteration":742,"passed_time":1.551673481,"remaining_time":0.5367161302},
{"learn":[0.1559839065],"iteration":743,"passed_time":1.553871749,"remaining_time":0.534665548},
{"learn":[0.1559052528],"iteration":744,"passed_time":1.556237068,"remaining_time":0.532671748},
{"learn":[0.1556908257],"iteration":745,"passed_time":1.558337619,"remaining_time":0.5305868033},
{"learn":[0.1555451283],"iteration":746,"passed_time":1.560486426,"remaining_time":0.5285181605},
{"learn":[0.1555156129],"iteration":747,"passed_time":1.561938906,"remaining_time":0.5262147117},
{"learn":[0.1554171884],"iteration":748,"passed_time":1.564559887,"remaining_time":0.5243051155},
{"learn":[0.1553437294],"iteration":749,"passed_time":1.566799035,"remaining_time":0.522266345},
{"learn":[0.155225016],"iteration":750,"passed_time":1.569115627,"remaining_time":0.5202527178},
{"learn":[0.1550664441],"iteration":751,"passed_time":1.571343067,"remaining_time":0.5182088837},
{"learn":[0.1548916875],"iteration":752,"passed_time":1.5731684,"remaining_time":0.5160326623},
{"learn":[0.1547300421],"iteration":753,"passed_time":1.575688838,"remaining_time":0.5140841566},
{"learn":[0.1545947892],"iteration":754,"passed_time":1.577612774,"remaining_time":0.5119405691},
{"learn":[0.1544190935],"iteration":755,"passed_time":1.5797668,"remaining_time":0.5098718242},
{"learn":[0.1543821519],"iteration":756,"passed_time":1.581989532,"remaining_time":0.5078249092},
{"learn":[0.1542029712],"iteration":757,"passed_time":1.584070825,"remaining_time":0.5057323742},
{"learn":[0.1540733006],"iteration":758,"passed_time":1.586336975,"remaining_time":0.5036985653},
{"learn":[0.1539413736],"iteration":759,"passed_time":1.588597444,"remaining_time":0.5016623509},
{"learn":[0.1537330595],"iteration":760,"passed_time":1.591112164,"remaining_time":0.4997053972},
{"learn":[0.1534669489],"iteration":761,"passed_time":1.593179387,"remaining_time":0.49760721},
{"learn":[0.1533514869],"iteration":762,"passed_time":1.595459442,"remaining_time":0.4955752134},
{"learn":[0.1532334286],"iteration":763,"passed_time":1.598235411,"remaining_time":0.4936957552},
{"learn":[0.1531345687],"iteration":764,"passed_time":1.600108064,"remaining_time":0.491536464},
{"learn":[0.1530434537],"iteration":765,"passed_time":1.602301985,"remaining_time":0.4894760632},
{"learn":[0.1529294548],"iteration":766,"passed_time":1.604964573,"remaining_time":0.4875576864},
{"learn":[0.1527704152],"iteration":767,"passed_time":1.607326119,"remaining_time":0.4855464318},
{"learn":[0.1526868286],"iteration":768,"passed_time":1.609393871,"remaining_time":0.4834460132},
{"learn":[0.1525512592],"iteration":769,"passed_time":1.611465848,"remaining_time":0.4813469417},
{"learn":[0.1524179436],"iteration":770,"passed_time":1.613883749,"remaining_time":0.4793506855},
{"learn":[0.1522721386],"iteration":771,"passed_time":1.615927777,"remaining_time":0.4772429187},
{"learn":[0.1522030632],"iteration":772,"passed_time":1.618845775,"remaining_time":0.4753919675},
{"learn":[0.1519559154],"iteration":773,"passed_time":1.620756648,"remaining_time":0.4732441893},
{"learn":[0.1518873881],"iteration":774,"passed_time":1.623150414,"remaining_time":0.4712372171},
{"learn":[0.1517510778],"iteration":775,"passed_time":1.625295939,"remaining_time":0.4691575906},
{"learn":[0.1516377838],"iteration":776,"passed_time":1.627346789,"remaining_time":0.4670506228},
{"learn":[0.1515543565],"iteration":777,"passed_time":1.629479608,"remaining_time":0.4649671889},
{"learn":[0.1513997416],"iteration":778,"passed_time":1.631771211,"remaining_time":0.4629286747},
{"learn":[0.1512315329],"iteration":779,"passed_time":1.633902176,"remaining_time":0.4608442035},
{"learn":[0.1510183157],"iteration":780,"passed_time":1.635844218,"remaining_time":0.4587066373},
{"learn":[0.1508752621],"iteration":781,"passed_time":1.637914503,"remaining_time":0.4566053218},
{"learn":[0.1507336746],"iteration":782,"passed_time":1.639970007,"remaining_time":0.4544999892},
{"learn":[0.1506140969],"iteration":783,"passed_time":1.641556352,"remaining_time":0.4522655254},
{"learn":[0.1504609937],"iteration":784,"passed_time":1.64354501,"remaining_time":0.4501429009},
{"learn":[0.1503390876],"iteration":785,"passed_time":1.645261258,"remaining_time":0.4479464494},
{"learn":[0.1502529519],"iteration":786,"passed_time":1.64687924,"remaining_time":0.4457246227},
{"learn":[0.150039311],"iteration":787,"passed_time":1.648771445,"remaining_time":0.4435781046},
{"learn":[0.149892062],"iteration":788,"passed_time":1.65037604,"remaining_time":0.4413553161},
{"learn":[0.1496687555],"iteration":789,"passed_time":1.652036958,"remaining_time":0.4391490648},
{"learn":[0.149580343],"iteration":790,"passed_time":1.653876186,"remaining_time":0.4369913058},
{"learn":[0.1492762865],"iteration":791,"passed_time":1.655705666,"remaining_time":0.4348317911},
{"learn":[0.1491204576],"iteration":792,"passed_time":1.657736398,"remaining_time":0.4327256425},
{"learn":[0.149056806],"iteration":793,"passed_time":1.659980371,"remaining_time":0.430675008},
{"learn":[0.1489496828],"iteration":794,"passed_time":1.661790591,"remaining_time":0.4285120391},
{"learn":[0.148845503],"iteration":795,"passed_time":1.663727004,"remaining_time":0.4263822976},
{"learn":[0.148656528],"iteration":796,"passed_time":1.665856322,"remaining_time":0.4243021748},
{"learn":[0.1484222858],"iteration":797,"passed_time":1.667609419,"remaining_time":0.422126695},
{"learn":[0.1482848108],"iteration":798,"passed_time":1.669363557,"remaining_time":0.4199525344},
{"learn":[0.1481391344],"iteration":799,"passed_time":1.672034732,"remaining_time":0.4180086829},
{"learn":[0.1480949298],"iteration":800,"passed_time":1.674150324,"remaining_time":0.4159249868},
{"learn":[0.1479384794],"iteration":801,"passed_time":1.676138311,"remaining_time":0.4138097078},
{"learn":[0.1478301084],"iteration":802,"passed_time":1.677634412,"remaining_time":0.4115740712},
{"learn":[0.1477149554],"iteration":803,"passed_time":1.679439686,"remaining_time":0.4094156448},
{"learn":[0.1475206314],"iteration":804,"passed_time":1.681333286,"remaining_time":0.4072794917},
{"learn":[0.1473574174],"iteration":805,"passed_time":1.683010307,"remaining_time":0.4050918108},
{"learn":[0.147208484],"iteration":806,"passed_time":1.684644051,"remaining_time":0.4028950457},
{"learn":[0.1471138883],"iteration":807,"passed_time":1.686725701,"remaining_time":0.4008061071},
{"learn":[0.1470460286],"iteration":808,"passed_time":1.688379722,"remaining_time":0.3986162261},
{"learn":[0.1469396526],"iteration":809,"passed_time":1.689891786,"remaining_time":0.3963943696},
{"learn":[0.1468784326],"iteration":810,"passed_time":1.691788907,"remaining_time":0.3942639994},
{"learn":[0.1468017595],"iteration":811,"passed_time":1.693478263,"remaining_time":0.3920861002},
{"learn":[0.1466709416],"iteration":812,"passed_time":1.69526762,"remaining_time":0.3899324045},
{"learn":[0.1465112357],"iteration":813,"passed_time":1.697321086,"remaining_time":0.3878399532},
{"learn":[0.146317974],"iteration":814,"passed_time":1.699067727,"remaining_time":0.3856779504},
{"learn":[0.1462354406],"iteration":815,"passed_time":1.701050049,"remaining_time":0.383570109},
{"learn":[0.1460839914],"iteration":816,"passed_time":1.703181796,"remaining_time":0.3814960449},
{"learn":[0.1459859404],"iteration":817,"passed_time":1.704915197,"remaining_time":0.37933321},
{"learn":[0.1458144314],"iteration":818,"passed_time":1.707242109,"remaining_time":0.3773025906},
{"learn":[0.1457133354],"iteration":819,"passed_time":1.709316828,"remaining_time":0.375215889},
{"learn":[0.1456420624],"iteration":820,"passed_time":1.711481572,"remaining_time":0.3731488446},
{"learn":[0.1454818233],"iteration":821,"passed_time":1.713715026,"remaining_time":0.3710964411},
{"learn":[0.1453588928],"iteration":822,"passed_time":1.715834981,"remaining_time":0.369019188},
{"learn":[0.145249629],"iteration":823,"passed_time":1.717778707,"remaining_time":0.3669041898},
{"learn":[0.1449990739],"iteration":824,"passed_time":1.719956494,"remaining_time":0.3648392563},
{"learn":[0.1449089137],"iteration":825,"passed_time":1.721776923,"remaining_time":0.3626987707},
{"learn":[0.1447749533],"iteration":826,"passed_time":1.723676821,"remaining_time":0.3605756833},
{"learn":[0.1447083465],"iteration":827,"passed_time":1.725708529,"remaining_time":0.3584805158},
{"learn":[0.1445364148],"iteration":828,"passed_time":1.727906916,"remaining_time":0.3564198826},
{"learn":[0.1443701424],"iteration":829,"passed_time":1.729897863,"remaining_time":0.3543164298},
{"learn":[0.1441865809],"iteration":830,"passed_time":1.732026767,"remaining_time":0.3522413041},
{"learn":[0.1440111274],"iteration":831,"passed_time":1.734324508,"remaining_time":0.350200141},
{"learn":[0.1438413432],"iteration":832,"passed_time":1.736440738,"remaining_time":0.3481219727},
{"learn":[0.1436274177],"iteration":833,"passed_time":1.738372023,"remaining_time":0.3460069014},
{"learn":[0.143506351],"iteration":834,"passed_time":1.74076536,"remaining_time":0.3439835741},
{"learn":[0.1433212623],"iteration":835,"passed_time":1.742635844,"remaining_time":0.3418567923},
{"learn":[0.1431410646],"iteration":836,"passed_time":1.744848371,"remaining_time":0.3397972336},
{"learn":[0.1430508922],"iteration":837,"passed_time":1.746655479,"remaining_time":0.3376589351},
{"learn":[0.1428957204],"iteration":838,"passed_time":1.748477186,"remaining_time":0.3355242276},
{"learn":[0.1427781392],"iteration":839,"passed_time":1.750285399,"remaining_time":0.333387695},
{"learn":[0.1425981448],"iteration":840,"passed_time":1.75197888,"remaining_time":0.331230252},
{"learn":[0.1425548169],"iteration":841,"passed_time":1.754363098,"remaining_time":0.3292035267},
{"learn":[0.1424049091],"iteration":842,"passed_time":1.756343863,"remaining_time":0.3271008144},
{"learn":[0.1422237403],"iteration":843,"passed_time":1.758144319,"remaining_time":0.3249650638},
{"learn":[0.1420817074],"iteration":844,"passed_time":1.760328436,"remaining_time":0.3229004823},
{"learn":[0.1419388989],"iteration":845,"passed_time":1.762121941,"remaining_time":0.3207645142},
{"learn":[0.1417155532],"iteration":846,"passed_time":1.76384083,"remaining_time":0.3186158761},
{"learn":[0.1416321554],"iteration":847,"passed_time":1.765823209,"remaining_time":0.3165154808},
{"learn":[0.1415347793],"iteration":848,"passed_time":1.767733052,"remaining_time":0.3144024627},
{"learn":[0.1413611119],"iteration":849,"passed_time":1.769376144,"remaining_time":0.312242849},
{"learn":[0.1411495461],"iteration":850,"passed_time":1.771383283,"remaining_time":0.3101481893},
{"learn":[0.1410343538],"iteration":851,"passed_time":1.773036924,"remaining_time":0.3079923295},
{"learn":[0.1407656982],"iteration":852,"passed_time":1.774727825,"remaining_time":0.3058440682},
{"learn":[0.1406164841],"iteration":853,"passed_time":1.776640398,"remaining_time":0.3037347754},
{"learn":[0.1404749273],"iteration":854,"passed_time":1.778313195,"remaining_time":0.3015852787},
{"learn":[0.1402775597],"iteration":855,"passed_time":1.780314487,"remaining_time":0.2994921567},
{"learn":[0.1402207604],"iteration":856,"passed_time":1.782390782,"remaining_time":0.2974117641},
{"learn":[0.1400837057],"iteration":857,"passed_time":1.784107139,"remaining_time":0.2952718109},
{"learn":[0.1399467538],"iteration":858,"passed_time":1.785928128,"remaining_time":0.2931500187},
{"learn":[0.1398059303],"iteration":859,"passed_time":1.78770553,"remaining_time":0.2910218304},
{"learn":[0.1397737778],"iteration":860,"passed_time":1.7893776,"remaining_time":0.2888774523},
{"learn":[0.1396642537],"iteration":861,"passed_time":1.791146154,"remaining_time":0.2867496162},
{"learn":[0.1395915288],"iteration":862,"passed_time":1.793282023,"remaining_time":0.2846809237},
{"learn":[0.1394658516],"iteration":863,"passed_time":1.795466903,"remaining_time":0.2826197902},
{"learn":[0.1394255704],"iteration":864,"passed_time":1.797906417,"remaining_time":0.2805981114},
{"learn":[0.1393235488],"iteration":865,"passed_time":1.799562671,"remaining_time":0.2784542701},
{"learn":[0.1391478365],"iteration":866,"passed_time":1.801164944,"remaining_time":0.2763032729},
{"learn":[0.1389662055],"iteration":867,"passed_time":1.803188835,"remaining_time":0.2742176569},
{"learn":[0.138748603],"iteration":868,"passed_time":1.804888343,"remaining_time":0.272083283},
{"learn":[0.1385716012],"iteration":869,"passed_time":1.806524915,"remaining_time":0.2699405046},
{"learn":[0.1383528248],"iteration":870,"passed_time":1.808497775,"remaining_time":0.2678486946},
{"learn":[0.1381645472],"iteration":871,"passed_time":1.810029463,"remaining_time":0.2656923982},
{"learn":[0.1380401265],"iteration":872,"passed_time":1.811780704,"remaining_time":0.2635694723},
{"learn":[0.1379477396],"iteration":873,"passed_time":1.813593265,"remaining_time":0.2614562372},
{"learn":[0.1377773507],"iteration":874,"passed_time":1.815359758,"remaining_time":0.2593371083},
{"learn":[0.1375847009],"iteration":875,"passed_time":1.81704612,"remaining_time":0.2572074416},
{"learn":[0.1374319387],"iteration":876,"passed_time":1.818894329,"remaining_time":0.2551014852},
{"learn":[0.1371893913],"iteration":877,"passed_time":1.820441616,"remaining_time":0.252954302},
{"learn":[0.1370260198],"iteration":878,"passed_time":1.822504426,"remaining_time":0.2508794489},
{"learn":[0.1369540062],"iteration":879,"passed_time":1.824775072,"remaining_time":0.2488329643},
{"learn":[0.1367654864],"iteration":880,"passed_time":1.826606794,"remaining_time":0.2467266838},
{"learn":[0.1365914752],"iteration":881,"passed_time":1.828541697,"remaining_time":0.2446348302},
{"learn":[0.1364683079],"iteration":882,"passed_time":1.830503443,"remaining_time":0.2425468888},
{"learn":[0.1363498578],"iteration":883,"passed_time":1.832237047,"remaining_time":0.2404292958},
{"learn":[0.1362742303],"iteration":884,"passed_time":1.834206389,"remaining_time":0.2383432031},
{"learn":[0.1361766946],"iteration":885,"passed_time":1.836580628,"remaining_time":0.2363094713},
{"learn":[0.1360206605],"iteration":886,"passed_time":1.838402226,"remaining_time":0.2342045677},
{"learn":[0.135837634],"iteration":887,"passed_time":1.840590098,"remaining_time":0.2321464989},
{"learn":[0.1356940529],"iteration":888,"passed_time":1.842292517,"remaining_time":0.2300275247},
{"learn":[0.1354738133],"iteration":889,"passed_time":1.843983533,"remaining_time":0.2279080771},
{"learn":[0.1354145731],"iteration":890,"passed_time":1.846164554,"remaining_time":0.2258495357},
{"learn":[0.1352878436],"iteration":891,"passed_time":1.848116826,"remaining_time":0.2237630238},
{"learn":[0.1351293287],"iteration":892,"passed_time":1.850169421,"remaining_time":0.2216888332},
{"learn":[0.1350208081],"iteration":893,"passed_time":1.852529623,"remaining_time":0.2196511633},
{"learn":[0.1348960789],"iteration":894,"passed_time":1.854430833,"remaining_time":0.2175589246},
{"learn":[0.1348063585],"iteration":895,"passed_time":1.856467356,"remaining_time":0.2154828181},
{"learn":[0.1347171896],"iteration":896,"passed_time":1.858227225,"remaining_time":0.2133750325},
{"learn":[0.1346003267],"iteration":897,"passed_time":1.86019472,"remaining_time":0.2112916052},
{"learn":[0.1345164324],"iteration":898,"passed_time":1.862247192,"remaining_time":0.2092179827},
{"learn":[0.1344081899],"iteration":899,"passed_time":1.864329731,"remaining_time":0.2071477479},
{"learn":[0.1343406507],"iteration":900,"passed_time":1.866296436,"remaining_time":0.2050647582},
{"learn":[0.1342151502],"iteration":901,"passed_time":1.868288175,"remaining_time":0.2029847463},
{"learn":[0.1341396518],"iteration":902,"passed_time":1.870187623,"remaining_time":0.200895016},
{"learn":[0.1339035306],"iteration":903,"passed_time":1.872369914,"remaining_time":0.1988357431},
{"learn":[0.1337537316],"iteration":904,"passed_time":1.874246703,"remaining_time":0.1967441291},
{"learn":[0.1336104974],"iteration":905,"passed_time":1.876490731,"remaining_time":0.1946910913},
{"learn":[0.1333711878],"iteration":906,"passed_time":1.878717065,"remaining_time":0.1926358181},
{"learn":[0.1333089756],"iteration":907,"passed_time":1.880687461,"remaining_time":0.1905542361},
{"learn":[0.133134396],"iteration":908,"passed_time":1.8828362,"remaining_time":0.1884907527},
{"learn":[0.1331071766],"iteration":909,"passed_time":1.884849719,"remaining_time":0.1864137085},
{"learn":[0.1329490022],"iteration":910,"passed_time":1.887241859,"remaining_time":0.184373793},
{"learn":[0.1328726291],"iteration":911,"passed_time":1.889146261,"remaining_time":0.1822860427},
{"learn":[0.1326739429],"iteration":912,"passed_time":1.891020675,"remaining_time":0.1801958365},
{"learn":[0.1324950769],"iteration":913,"passed_time":1.893232971,"remaining_time":0.1781378944},
{"learn":[0.1323460624],"iteration":914,"passed_time":1.895615909,"remaining_time":0.176095467},
{"learn":[0.1322898318],"iteration":915,"passed_time":1.89763947,"remaining_time":0.17401934},
{"learn":[0.131986313],"iteration":916,"passed_time":1.899544729,"remaining_time":0.1719326199},
{"learn":[0.131774381],"iteration":917,"passed_time":1.901420057,"remaining_time":0.1698436216},
{"learn":[0.1315953257],"iteration":918,"passed_time":1.903473362,"remaining_time":0.1677707751},
{"learn":[0.1313485031],"iteration":919,"passed_time":1.905448558,"remaining_time":0.165691179},
{"learn":[0.1311940603],"iteration":920,"passed_time":1.907172937,"remaining_time":0.1635902953},
{"learn":[0.1311043339],"iteration":921,"passed_time":1.909127471,"remaining_time":0.1615096993},
{"learn":[0.1310671623],"iteration":922,"passed_time":1.911168506,"remaining_time":0.1594365926},
{"learn":[0.1309555742],"iteration":923,"passed_time":1.913267507,"remaining_time":0.1573683231},
{"learn":[0.1308838268],"iteration":924,"passed_time":1.91534206,"remaining_time":0.1552980048},
{"learn":[0.1308438985],"iteration":925,"passed_time":1.917093413,"remaining_time":0.1532018494},
{"learn":[0.1307378293],"iteration":926,"passed_time":1.919864844,"remaining_time":0.1511867677},
{"learn":[0.1306161517],"iteration":927,"passed_time":1.922477817,"remaining_time":0.1491577617},
{"learn":[0.1304687637],"iteration":928,"passed_time":1.925241541,"remaining_time":0.1471390198},
{"learn":[0.1303684502],"iteration":929,"passed_time":1.927525394,"remaining_time":0.1450825566},
{"learn":[0.1302951208],"iteration":930,"passed_time":1.929877057,"remaining_time":0.1430306304},
{"learn":[0.1301538225],"iteration":931,"passed_time":1.93199999,"remaining_time":0.1409613727},
{"learn":[0.129986254],"iteration":932,"passed_time":1.934257252,"remaining_time":0.1389016462},
{"learn":[0.1298813759],"iteration":933,"passed_time":1.936180179,"remaining_time":0.1368178714},
{"learn":[0.1297482353],"iteration":934,"passed_time":1.938320179,"remaining_time":0.1347495312},
{"learn":[0.1296439495],"iteration":935,"passed_time":1.940802714,"remaining_time":0.132704459},
{"learn":[0.1296159566],"iteration":936,"passed_time":1.942758683,"remaining_time":0.1306230491},
{"learn":[0.1294490137],"iteration":937,"passed_time":1.944897725,"remaining_time":0.1285540074},
{"learn":[0.1294006165],"iteration":938,"passed_time":1.946886486,"remaining_time":0.126475054},
{"learn":[0.1292897974],"iteration":939,"passed_time":1.949020483,"remaining_time":0.1244055627},
{"learn":[0.1290351805],"iteration":940,"passed_time":1.951484267,"remaining_time":0.1223566118},
{"learn":[0.1288972651],"iteration":941,"passed_time":1.953419726,"remaining_time":0.1202742506},
{"learn":[0.1288716895],"iteration":942,"passed_time":1.955544826,"remaining_time":0.1182036639},
{"learn":[0.1287881972],"iteration":943,"passed_time":1.957414509,"remaining_time":0.1161178099},
{"learn":[0.1286278925],"iteration":944,"passed_time":1.959514393,"remaining_time":0.1140458112},
{"learn":[0.1285143552],"iteration":945,"passed_time":1.961724558,"remaining_time":0.1119800487},
{"learn":[0.1284999666],"iteration":946,"passed_time":1.963881669,"remaining_time":0.1099110121},
{"learn":[0.1284140924],"iteration":947,"passed_time":1.965937563,"remaining_time":0.1078362376},
{"learn":[0.1283033643],"iteration":948,"passed_time":1.968007152,"remaining_time":0.1057622389},
{"learn":[0.1281985827],"iteration":949,"passed_time":1.970254967,"remaining_time":0.1036976299},
{"learn":[0.1280428768],"iteration":950,"passed_time":1.972637323,"remaining_time":0.1016395676},
{"learn":[0.1279243076],"iteration":951,"passed_time":1.97451541,"remaining_time":0.09955539884},
{"learn":[0.1278512435],"iteration":952,"passed_time":1.9765246,"remaining_time":0.09747812821},
{"learn":[0.1277254506],"iteration":953,"passed_time":1.978992153,"remaining_time":0.0954231017},
{"learn":[0.127617784],"iteration":954,"passed_time":1.98127536,"remaining_time":0.09335852479},
{"learn":[0.1274339763],"iteration":955,"passed_time":1.983452173,"remaining_time":0.09128859371},
{"learn":[0.1273888799],"iteration":956,"passed_time":1.985273599,"remaining_time":0.08920247103},
{"learn":[0.1272602613],"iteration":957,"passed_time":1.987721356,"remaining_time":0.08714436008},
{"learn":[0.1270681961],"iteration":958,"passed_time":1.989793714,"remaining_time":0.08506938715},
{"learn":[0.1268564177],"iteration":959,"passed_time":1.992181007,"remaining_time":0.08300754195},
{"learn":[0.1267808011],"iteration":960,"passed_time":1.994435453,"remaining_time":0.08093962816},
{"learn":[0.1265906062],"iteration":961,"passed_time":1.996480436,"remaining_time":0.07886305255},
{"learn":[0.1264674217],"iteration":962,"passed_time":1.998675818,"remaining_time":0.07679232115},
{"learn":[0.1263482835],"iteration":963,"passed_time":2.000312156,"remaining_time":0.07470045395},
{"learn":[0.1262290105],"iteration":964,"passed_time":2.002075692,"remaining_time":0.07261414425},
{"learn":[0.126156777],"iteration":965,"passed_time":2.003955985,"remaining_time":0.07053261231},
{"learn":[0.1258322425],"iteration":966,"passed_time":2.005643834,"remaining_time":0.0684449292},
{"learn":[0.1257649048],"iteration":967,"passed_time":2.007365065,"remaining_time":0.06635917571},
{"learn":[0.1256570779],"iteration":968,"passed_time":2.009130382,"remaining_time":0.06427558499},
{"learn":[0.1254738884],"iteration":969,"passed_time":2.010712935,"remaining_time":0.06218699799},
{"learn":[0.1253428523],"iteration":970,"passed_time":2.012334664,"remaining_time":0.06010062332},
{"learn":[0.1252558899],"iteration":971,"passed_time":2.014279768,"remaining_time":0.05802452005},
{"learn":[0.1251430242],"iteration":972,"passed_time":2.01621859,"remaining_time":0.05594851176},
{"learn":[0.1249880377],"iteration":973,"passed_time":2.018266056,"remaining_time":0.05387568526},
{"learn":[0.1249287741],"iteration":974,"passed_time":2.020129939,"remaining_time":0.05179820357},
{"learn":[0.1248219821],"iteration":975,"passed_time":2.021790297,"remaining_time":0.04971615483},
{"learn":[0.1246911988],"iteration":976,"passed_time":2.023887404,"remaining_time":0.04764525106},
{"learn":[0.1245607159],"iteration":977,"passed_time":2.025776765,"remaining_time":0.04556962048},
{"learn":[0.1245168075],"iteration":978,"passed_time":2.027578778,"remaining_time":0.04349249676},
{"learn":[0.1242737916],"iteration":979,"passed_time":2.029531796,"remaining_time":0.04141901624},
{"learn":[0.1241020464],"iteration":980,"passed_time":2.031465192,"remaining_time":0.03934540127},
{"learn":[0.1240084017],"iteration":981,"passed_time":2.03341813,"remaining_time":0.03727243008},
{"learn":[0.123869546],"iteration":982,"passed_time":2.035576131,"remaining_time":0.03520324947},
{"learn":[0.1238061556],"iteration":983,"passed_time":2.037200197,"remaining_time":0.03312520645},
{"learn":[0.1236529975],"iteration":984,"passed_time":2.038819202,"remaining_time":0.03104800815},
{"learn":[0.1235194377],"iteration":985,"passed_time":2.040731004,"remaining_time":0.0289758966},
{"learn":[0.1234239317],"iteration":986,"passed_time":2.042875749,"remaining_time":0.02690717806},
{"learn":[0.1234203885],"iteration":987,"passed_time":2.044112761,"remaining_time":0.0248272805},
{"learn":[0.1233321621],"iteration":988,"passed_time":2.046468981,"remaining_time":0.02276153569},
{"learn":[0.123275432],"iteration":989,"passed_time":2.048118093,"remaining_time":0.02068806155},
{"learn":[0.1231810822],"iteration":990,"passed_time":2.049745638,"remaining_time":0.01861524797},
{"learn":[0.1230489486],"iteration":991,"passed_time":2.051651711,"remaining_time":0.01654557831},
{"learn":[0.1229303782],"iteration":992,"passed_time":2.053363679,"remaining_time":0.01447486984},
{"learn":[0.1228135191],"iteration":993,"passed_time":2.055240434,"remaining_time":0.01240587787},
{"learn":[0.1227986168],"iteration":994,"passed_time":2.057264482,"remaining_time":0.01033801247},
{"learn":[0.122637241],"iteration":995,"passed_time":2.058906238,"remaining_time":0.00826869975},
{"learn":[0.1224362746],"iteration":996,"passed_time":2.060658848,"remaining_time":0.006200578279},
{"learn":[0.1221795638],"iteration":997,"passed_time":2.062716837,"remaining_time":0.004133701076},
{"learn":[0.1220705328],"iteration":998,"passed_time":2.064197444,"remaining_time":0.002066263708},
{"learn":[0.1220507075],"iteration":999,"passed_time":2.065793912,"remaining_time":0}
]}